ex2/register_stage.v
module register_stage #(parameter WIDTH=32) (input wire clk, input wire res_n,
                                   input wire[WIDTH-1:0] fill_in, input wire[WIDTH-1:0] fwd_in, output reg[WIDTH-1:0] data_out,
                                   input wire shift_in, input wire shift_out,
                                   input wire prev_filled, output reg filled
                                  );

	always @(posedge clk or negedge res_n)
	begin
		if (res_n == 1'b0)
		begin
			data_out <= {WIDTH{1'b0}};
			filled <= 1'b0;
		end
		else
		begin
			case({shift_in,shift_out})
				2'b00: // Do nothing
				begin
					data_out <= data_out;
					filled <= filled;
				end
				2'b01: // All register stages shift one forward.
				begin
					data_out <= fwd_in;
					filled <= prev_filled;
				end
				2'b10: // Fill in a new value without shifting.
				begin
					data_out <= fill_in;
					filled <= 1'b1;
				end
				2'b11:
				begin
					data_out <= fill_in;
					filled <= 1'b1;
				end
			endcase
		end
	end
endmodule

ex2/ser_64_16.v
`default_nettype none
module ser_64_16 #(parameter INWIDTH=64, parameter OUTWIDTH=16) (input wire clk, input wire res_n,
                                                                 input wire[INWIDTH-1:0] wdata, output wire[OUTWIDTH-1:0] rdata,
                                                                 input wire valid_in, output wire valid_out,
                                                                 output wire stop_out, input wire stop_in
                                                                );

parameter DEPTH = INWIDTH/OUTWIDTH;
// Here should be an assert to ensure the division works without a remainder

wire[OUTWIDTH-1:0] data [DEPTH:0];
wire[DEPTH:0] filled;

assign valid_out=filled[DEPTH];
assign stop_out=stop_in?1'b1:filled[DEPTH-1]; // Vorletzte Stufe leer, dann kann im nächten Takt das nächste Datum kommen.


wire shift_out;
assign shift_out = !stop_in;
//assign shift_out = 1'b0;

wire shift_in;
assign shift_in = !filled[DEPTH-1] && !stop_in && valid_in;



`ifdef DEBUG
assign data[0] = {OUTWIDTH{1'b1}}; // For debugging: If there are all ones, they must have come from here...
`else
assign data[0] = {OUTWIDTH{1'b0}}; // ... in normal operation, zeros are more common.
`endif
assign rdata = data[DEPTH];
assign filled[0]       = 1'b0;

generate
	genvar i;
	for(i=0; i<DEPTH; i=i+1)
	begin : foobar
		register_stage #(.WIDTH(OUTWIDTH)) stage_I (.clk(clk), .res_n(res_n),
		                                         .fill_in(wdata[OUTWIDTH*(i+1)-1:OUTWIDTH*i]), .fwd_in(data[i]), .data_out(data[i+1]),
		                                         .shift_in(shift_in), .shift_out(shift_out),
		                                         .prev_filled(filled[i]), .filled(filled[i+1])
		                                        );
	end
endgenerate

//{{{ Console output

`ifdef VERBOSE
integer j;
always @(posedge clk)
begin
	#1
	$write("%c[1;34m%m: STATUS:", 27);
	if(shift_in == 1'b1)
		$write(" => %h ", wdata);
	else
		$write(" -> %h ", wdata);
	for (j = 1; j != DEPTH+1; j = j + 1)
	begin
		if(filled[j] == 1'b1)
			$write("■");
		else
			$write("◻");
	end
	if(shift_out == 1'b1)
		$write(" => %h", rdata);
	else
		$write(" -> %h", rdata);
	if(stop_out == 1'b1)
		$write(" STOP");
	if(valid_out == 1'b1)
		$write(" VALID");
	if(res_n == 1'b0)
		$write(" RESET");
	$display("%c[0m", 27);
end
`endif
//}}}

endmodule

ex2/ser_64_16_tb.v
		//$write(" ◻◼▯■□●◯◾◾◽ Address = %g",j);
`default_nettype none
//`timescale 1ns/1ns

module ser_64_16_tb;
parameter INWIDTH=64;
parameter OUTWIDTH=16;
parameter DEPTH = INWIDTH/OUTWIDTH;

	//{{{
	/* Make a regular pulsing clock. */
	parameter clk_period=10;
	parameter half_clk_period=5;
	reg clk = 1;
	always begin
		#half_clk_period
		//$display("clk \\");
		clk = 1'b0;

		#half_clk_period
		`ifdef SHOWCLOCK
			$display("clk /");
		`endif
		clk = 1'b1;
	end

	//{{{ Resynchronise the testbench to the clock

	task resync; // Used to phase-shift the testbench to align on the falling edge of the clock.
	begin        // They get out of phase, when crooked wait times are used, for example to generate an asyncronous reset.
		#(clk_period+half_clk_period-($time%clk_period));
	end
	endtask
	//}}}

	//}}}


	//{{{ Signals and module instantiation
	reg res_n = 0;

	reg[INWIDTH-1:0] indata={INWIDTH{1'b0}};
	wire[OUTWIDTH-1:0] outdata;
	reg valid_in;
	reg stop_in;
	wire stop_out;
	wire valid_out;

	ser_64_16 #(.INWIDTH(INWIDTH), .OUTWIDTH(OUTWIDTH)) ser_64_16_I(.clk(clk), .res_n(res_n),
	                                                                .wdata(indata), .rdata(outdata),
	                                                                .valid_in(valid_in), .valid_out(valid_out),
	                                                                .stop_out(stop_out), .stop_in(stop_in)
	                                                               );
	//}}}


	//{{{ Messages, pretty printed

	task pass;
	begin
		$display("%c[1;32m",27);
		$display("***************************************");
		$display("*********** TEST CASE PASS ************");
		$display("***************************************");
		$write("%c[0m",27);
	end
	endtask

	task fail;
	begin
		$display("%c[1;31m",27);
		$display("***************************************");
		$display("*********** TEST CASE FAIL ************");
		$display("***************************************");
		$display("%c[0m",27);
		`ifdef FAILABORT
			$finish;
		`endif
	end
	endtask

	task success;
	begin
			$display("%c[1;32m-----------------------------------------------------------> SUCCESS.%c[0m\n", 27, 27);
	end
	endtask

	task defeat;
	begin
			$display("%c[1;31m-----------------------------------------------------------> FAILED.%c[0m\n", 27, 27);
			fail;
	end
	endtask
	//}}}


	//{{{ Check the module output

	task check_ser_64_16(input[OUTWIDTH-1:0] outdata, input[OUTWIDTH-1:0] expected_outdata, input stop_out, input expected_stop_out, input valid_out, input expected_valid_out);
	begin
		if(valid_out !== expected_valid_out)
		begin
			$display("%c[1;31mFIFO TEST: Expected valid_out = %b but got %b.%c[0m", 27, expected_valid_out, valid_out, 27);
			defeat;
		end
		if(stop_out !== expected_stop_out)
		begin
			$display("%c[1;31mFIFO TEST: Expected stop_out = %b but got %b.%c[0m", 27, expected_stop_out, stop_out, 27);
			defeat;
		end
		if(^expected_outdata!==1'bX && expected_valid_out == 1'b0 && outdata !== expected_outdata)
		begin
			$display("%c[1;31mFIFO TEST: Expected output = %h but got %h.%c[0m", 27, expected_outdata, outdata, 27);
			defeat;
		end
	end
	endtask
	//}}}


	//{{{ Parameters and Variables for testing

	parameter VL=26;
reg[OUTWIDTH-1:0] TESTVECTOR[VL-1:0];

	//}}}

integer write=0;
integer read=0;
	initial begin
	//{{{ Dump the waveform to file for reading with gtkwave.

	`ifdef DUMP_DATA
		$dumpfile("ser_64_16.vcd");
		$dumpvars(0, ser_64_16_tb);
	`endif
	//}}}

	//{{{ Initialise TESTVECTOR

	TESTVECTOR[ 0] = 16'haffe;
	TESTVECTOR[ 1] = 16'hcafe;
	TESTVECTOR[ 2] = 16'hbabe;
	TESTVECTOR[ 3] = 16'hb00b;
	TESTVECTOR[ 4] = 16'hc001;
	TESTVECTOR[ 5] = 16'hf00d;
	TESTVECTOR[ 6] = 16'hdead;
	TESTVECTOR[ 7] = 16'hbeef;
	TESTVECTOR[ 8] = 16'hc0de;
	TESTVECTOR[ 9] = 16'hfa11;
	TESTVECTOR[10] = 16'hface;
	TESTVECTOR[11] = 16'hfee1;
	TESTVECTOR[12] = 16'h0123;
	TESTVECTOR[13] = 16'h4567;
	TESTVECTOR[14] = 16'h89ab;
	TESTVECTOR[15] = 16'hcdef;
	TESTVECTOR[16] = 16'h1111;
	TESTVECTOR[17] = 16'h2222;
	TESTVECTOR[18] = 16'h3333;
	TESTVECTOR[19] = 16'h4444;
	TESTVECTOR[20] = 16'h5555;
	TESTVECTOR[21] = 16'h6666;
	TESTVECTOR[22] = 16'h7777;
	TESTVECTOR[23] = 16'h8888;
	TESTVECTOR[24] = 16'h9999;
	TESTVECTOR[25] = 16'ha5a5;
	//}}}

	valid_in  <= 1'b0;
	stop_in <= 1'b0;
	indata <= {INWIDTH{1'b0}};
	#half_clk_period
	res_n <= 1;


	$display("STARTING Fill And Drain TEST:");
	check_ser_64_16(outdata, {OUTWIDTH{1'bx}}, stop_out, 0, valid_out, 0);

	valid_in <= 1; write <= write+4;
	indata <= {TESTVECTOR[(write+0)%VL], TESTVECTOR[(write+1)%VL], TESTVECTOR[(write+2)%VL], TESTVECTOR[(write+3)%VL]};
	stop_in <= 0; read++;
	#clk_period;
	check_ser_64_16(outdata, TESTVECTOR[read%VL], stop_out, 1, valid_out, 1);

	valid_in <= 1; //write <= write+4;
	indata <= {TESTVECTOR[(write+0)%VL], TESTVECTOR[(write+1)%VL], TESTVECTOR[(write+2)%VL], TESTVECTOR[(write+3)%VL]};
	stop_in <= 0; read++;
	#clk_period;
	check_ser_64_16(outdata, TESTVECTOR[read%VL], stop_out, 1, valid_out, 1);

	valid_in <= 1; //write <= write+4;
	indata <= {TESTVECTOR[(write+0)%VL], TESTVECTOR[(write+1)%VL], TESTVECTOR[(write+2)%VL], TESTVECTOR[(write+3)%VL]};
	stop_in <= 0; read++;
	#clk_period;
	check_ser_64_16(outdata, TESTVECTOR[read%VL], stop_out, 1, valid_out, 1);

	valid_in <= 1; //write <= write+4;
	indata <= {TESTVECTOR[(write+0)%VL], TESTVECTOR[(write+1)%VL], TESTVECTOR[(write+2)%VL], TESTVECTOR[(write+3)%VL]};
	stop_in <= 0; read++;
	#clk_period;
	check_ser_64_16(outdata, TESTVECTOR[read%VL], stop_out, 0, valid_out, 1);

	$display("");

	valid_in <= 1; write <= write+4;
	indata <= {TESTVECTOR[(write+0)%VL], TESTVECTOR[(write+1)%VL], TESTVECTOR[(write+2)%VL], TESTVECTOR[(write+3)%VL]};
	stop_in <= 0; read++;
	#clk_period;
	check_ser_64_16(outdata, TESTVECTOR[read%VL], stop_out, 1, valid_out, 1);

	valid_in <= 0; //write <= write+4;
	indata <= {TESTVECTOR[(write+0)%VL], TESTVECTOR[(write+1)%VL], TESTVECTOR[(write+2)%VL], TESTVECTOR[(write+3)%VL]};
	stop_in <= 0; read++;
	#clk_period;
	check_ser_64_16(outdata, TESTVECTOR[read%VL], stop_out, 1, valid_out, 1);

	valid_in <= 0; //write <= write+4;
	indata <= {TESTVECTOR[(write+0)%VL], TESTVECTOR[(write+1)%VL], TESTVECTOR[(write+2)%VL], TESTVECTOR[(write+3)%VL]};
	stop_in <= 0; read++;
	#clk_period;
	check_ser_64_16(outdata, TESTVECTOR[read%VL], stop_out, 1, valid_out, 1);

	valid_in <= 0; //write <= write+4;
	indata <= {TESTVECTOR[(write+0)%VL], TESTVECTOR[(write+1)%VL], TESTVECTOR[(write+2)%VL], TESTVECTOR[(write+3)%VL]};
	stop_in <= 0; read++;
	#clk_period;
	check_ser_64_16(outdata, TESTVECTOR[read%VL], stop_out, 0, valid_out, 1);
	success;


	$display("STARTING Fill And Drain with STOPs TEST:");
	//check_ser_64_16(outdata, {OUTWIDTH{1'bx}}, stop_out, 0, valid_out, 0);
	check_ser_64_16(outdata, TESTVECTOR[read%VL], stop_out, 0, valid_out, 1);

	$display("/stop");
	valid_in <= 0; //write <= write+4;
	indata <= {TESTVECTOR[(write+0)%VL], TESTVECTOR[(write+1)%VL], TESTVECTOR[(write+2)%VL], TESTVECTOR[(write+3)%VL]};
	stop_in <= 0; //read++;
	#clk_period;
	check_ser_64_16(outdata, {OUTWIDTH{1'b1}}, stop_out, 0, valid_out, 0);

	valid_in <= 0; //write <= write+4;
	indata <= {TESTVECTOR[(write+0)%VL], TESTVECTOR[(write+1)%VL], TESTVECTOR[(write+2)%VL], TESTVECTOR[(write+3)%VL]};
	stop_in <= 0; //read++;
	#clk_period;
	check_ser_64_16(outdata, {OUTWIDTH{1'b1}}, stop_out, 0, valid_out, 0);

	valid_in <= 0; //write <= write+4;
	indata <= {TESTVECTOR[(write+0)%VL], TESTVECTOR[(write+1)%VL], TESTVECTOR[(write+2)%VL], TESTVECTOR[(write+3)%VL]};
	stop_in <= 1; //read++;
	#clk_period;
	check_ser_64_16(outdata, {OUTWIDTH{1'b1}}, stop_out, 1, valid_out, 0);

	valid_in <= 0; //write <= write+4;
	indata <= {TESTVECTOR[(write+0)%VL], TESTVECTOR[(write+1)%VL], TESTVECTOR[(write+2)%VL], TESTVECTOR[(write+3)%VL]};
	stop_in <= 1; //read++;
	#clk_period;
	check_ser_64_16(outdata, {OUTWIDTH{1'b1}}, stop_out, 1, valid_out, 0);

	$display("\\stop");

	valid_in <= 1; write <= write+4;
	indata <= {TESTVECTOR[(write+0)%VL], TESTVECTOR[(write+1)%VL], TESTVECTOR[(write+2)%VL], TESTVECTOR[(write+3)%VL]};
	stop_in <= 0; read++;
	#clk_period;
	check_ser_64_16(outdata, TESTVECTOR[read%VL], stop_out, 1, valid_out, 1);


	$display("/stop");
	valid_in <= 0; //write <= write+4;
	indata <= {TESTVECTOR[(write+0)%VL], TESTVECTOR[(write+1)%VL], TESTVECTOR[(write+2)%VL], TESTVECTOR[(write+3)%VL]};
	stop_in <= 1; //read++;
	#clk_period;
	check_ser_64_16(outdata, {OUTWIDTH{1'b1}}, stop_out, 1, valid_out, 1);

	valid_in <= 0; //write <= write+4;
	indata <= {TESTVECTOR[(write+0)%VL], TESTVECTOR[(write+1)%VL], TESTVECTOR[(write+2)%VL], TESTVECTOR[(write+3)%VL]};
	stop_in <= 1; //read++;
	#clk_period;
	check_ser_64_16(outdata, {OUTWIDTH{1'b1}}, stop_out, 1, valid_out, 1);
	$display("\\stop");


	valid_in <= 1; //write <= write+4;
	indata <= {TESTVECTOR[(write+0)%VL], TESTVECTOR[(write+1)%VL], TESTVECTOR[(write+2)%VL], TESTVECTOR[(write+3)%VL]};
	stop_in <= 0; read++;
	#clk_period;
	check_ser_64_16(outdata, TESTVECTOR[read%VL], stop_out, 1, valid_out, 1);

	$display("/stop");
	valid_in <= 1; //write <= write+4;
	indata <= {TESTVECTOR[(write+0)%VL], TESTVECTOR[(write+1)%VL], TESTVECTOR[(write+2)%VL], TESTVECTOR[(write+3)%VL]};
	stop_in <= 1; //read++;
	#clk_period;
	check_ser_64_16(outdata, {OUTWIDTH{1'b1}}, stop_out, 1, valid_out, 1);

	valid_in <= 1; //write <= write+4;
	indata <= {TESTVECTOR[(write+0)%VL], TESTVECTOR[(write+1)%VL], TESTVECTOR[(write+2)%VL], TESTVECTOR[(write+3)%VL]};
	stop_in <= 1; //read++;
	#clk_period;
	check_ser_64_16(outdata, {OUTWIDTH{1'b1}}, stop_out, 1, valid_out, 1);
	$display("\\stop");

	valid_in <= 1; //write <= write+4;
	indata <= {TESTVECTOR[(write+0)%VL], TESTVECTOR[(write+1)%VL], TESTVECTOR[(write+2)%VL], TESTVECTOR[(write+3)%VL]};
	stop_in <= 0; read++;
	#clk_period;
	check_ser_64_16(outdata, TESTVECTOR[read%VL], stop_out, 1, valid_out, 1);

	$display("/stop");
	valid_in <= 1; //write <= write+4;
	indata <= {TESTVECTOR[(write+0)%VL], TESTVECTOR[(write+1)%VL], TESTVECTOR[(write+2)%VL], TESTVECTOR[(write+3)%VL]};
	stop_in <= 1; //read++;
	#clk_period;
	check_ser_64_16(outdata, {OUTWIDTH{1'b1}}, stop_out, 1, valid_out, 1);

	valid_in <= 1; //write <= write+4;
	indata <= {TESTVECTOR[(write+0)%VL], TESTVECTOR[(write+1)%VL], TESTVECTOR[(write+2)%VL], TESTVECTOR[(write+3)%VL]};
	stop_in <= 1; //read++;
	#clk_period;
	check_ser_64_16(outdata, {OUTWIDTH{1'b1}}, stop_out, 1, valid_out, 1);
	$display("\\stop");

	valid_in <= 1; //write <= write+4;
	indata <= {TESTVECTOR[(write+0)%VL], TESTVECTOR[(write+1)%VL], TESTVECTOR[(write+2)%VL], TESTVECTOR[(write+3)%VL]};
	stop_in <= 0; read++;
	#clk_period;
	check_ser_64_16(outdata, TESTVECTOR[read%VL], stop_out, 0, valid_out, 1);

	$display("");

	valid_in <= 1; write <= write+4;
	indata <= {TESTVECTOR[(write+0)%VL], TESTVECTOR[(write+1)%VL], TESTVECTOR[(write+2)%VL], TESTVECTOR[(write+3)%VL]};
	stop_in <= 0; read++;
	#clk_period;
	check_ser_64_16(outdata, TESTVECTOR[read%VL], stop_out, 1, valid_out, 1);

	$display("/stop");
	valid_in <= 1; //write <= write+4;
	indata <= {TESTVECTOR[(write+0)%VL], TESTVECTOR[(write+1)%VL], TESTVECTOR[(write+2)%VL], TESTVECTOR[(write+3)%VL]};
	stop_in <= 1; //read++;
	#clk_period;
	check_ser_64_16(outdata, {OUTWIDTH{1'b1}}, stop_out, 1, valid_out, 1);

	valid_in <= 1; //write <= write+4;
	indata <= {TESTVECTOR[(write+0)%VL], TESTVECTOR[(write+1)%VL], TESTVECTOR[(write+2)%VL], TESTVECTOR[(write+3)%VL]};
	stop_in <= 1; //read++;
	#clk_period;
	check_ser_64_16(outdata, {OUTWIDTH{1'b1}}, stop_out, 1, valid_out, 1);
	$display("\\stop");

	valid_in <= 0; //write <= write+4;
	indata <= {TESTVECTOR[(write+0)%VL], TESTVECTOR[(write+1)%VL], TESTVECTOR[(write+2)%VL], TESTVECTOR[(write+3)%VL]};
	stop_in <= 0; read++;
	#clk_period;
	check_ser_64_16(outdata, TESTVECTOR[read%VL], stop_out, 1, valid_out, 1);

	valid_in <= 0; //write <= write+4;
	indata <= {TESTVECTOR[(write+0)%VL], TESTVECTOR[(write+1)%VL], TESTVECTOR[(write+2)%VL], TESTVECTOR[(write+3)%VL]};
	stop_in <= 0; read++;
	#clk_period;
	check_ser_64_16(outdata, TESTVECTOR[read%VL], stop_out, 1, valid_out, 1);

	valid_in <= 0; //write <= write+4;
	indata <= {TESTVECTOR[(write+0)%VL], TESTVECTOR[(write+1)%VL], TESTVECTOR[(write+2)%VL], TESTVECTOR[(write+3)%VL]};
	stop_in <= 0; read++;
	#clk_period;
	check_ser_64_16(outdata, TESTVECTOR[read%VL], stop_out, 0, valid_out, 1);
	success;









	$display("END");
	pass;
	$finish;
	end
endmodule

ex2/ser_64_16.vcd
$date
	Wed Feb 24 18:22:04 2016
$end
$version
	Icarus Verilog
$end
$timescale
	1s
$end
$scope module ser_64_16_tb $end
$var wire 1 ! valid_out $end
$var wire 1 " stop_out $end
$var wire 16 # outdata [15:0] $end
$var reg 1 $ clk $end
$var reg 64 % indata [63:0] $end
$var reg 1 & res_n $end
$var reg 1 ' stop_in $end
$var reg 1 ( valid_in $end
$var integer 32 ) read [31:0] $end
$var integer 32 * write [31:0] $end
$scope module ser_64_16_I $end
$var wire 1 $ clk $end
$var wire 16 + rdata [15:0] $end
$var wire 1 & res_n $end
$var wire 1 , shift_in $end
$var wire 1 ' stop_in $end
$var wire 1 ( valid_in $end
$var wire 64 - wdata [63:0] $end
$var wire 1 ! valid_out $end
$var wire 1 " stop_out $end
$var wire 1 . shift_out $end
$var wire 5 / filled [4:0] $end
$var integer 32 0 j [31:0] $end
$scope begin foobar[0] $end
$scope module stage_I $end
$var wire 1 $ clk $end
$var wire 16 1 fill_in [15:0] $end
$var wire 16 2 fwd_in [15:0] $end
$var wire 1 3 prev_filled $end
$var wire 1 & res_n $end
$var wire 1 , shift_in $end
$var wire 1 . shift_out $end
$var reg 16 4 data_out [15:0] $end
$var reg 1 5 filled $end
$upscope $end
$upscope $end
$scope begin foobar[1] $end
$scope module stage_I $end
$var wire 1 $ clk $end
$var wire 16 6 fill_in [15:0] $end
$var wire 16 7 fwd_in [15:0] $end
$var wire 1 8 prev_filled $end
$var wire 1 & res_n $end
$var wire 1 , shift_in $end
$var wire 1 . shift_out $end
$var reg 16 9 data_out [15:0] $end
$var reg 1 : filled $end
$upscope $end
$upscope $end
$scope begin foobar[2] $end
$scope module stage_I $end
$var wire 1 $ clk $end
$var wire 16 ; fill_in [15:0] $end
$var wire 16 < fwd_in [15:0] $end
$var wire 1 = prev_filled $end
$var wire 1 & res_n $end
$var wire 1 , shift_in $end
$var wire 1 . shift_out $end
$var reg 16 > data_out [15:0] $end
$var reg 1 ? filled $end
$upscope $end
$upscope $end
$scope begin foobar[3] $end
$scope module stage_I $end
$var wire 1 $ clk $end
$var wire 16 @ fill_in [15:0] $end
$var wire 16 A fwd_in [15:0] $end
$var wire 1 B prev_filled $end
$var wire 1 & res_n $end
$var wire 1 , shift_in $end
$var wire 1 . shift_out $end
$var reg 16 C data_out [15:0] $end
$var reg 1 D filled $end
$upscope $end
$upscope $end
$upscope $end
$scope task check_ser_64_16 $end
$var reg 16 E expected_outdata [15:0] $end
$var reg 1 F expected_stop_out $end
$var reg 1 G expected_valid_out $end
$var reg 16 H outdata [15:0] $end
$var reg 1 I stop_out $end
$var reg 1 J valid_out $end
$upscope $end
$scope task defeat $end
$upscope $end
$scope task fail $end
$upscope $end
$scope task pass $end
$upscope $end
$scope task resync $end
$upscope $end
$scope task success $end
$upscope $end
$upscope $end
$enddefinitions $end
#0
$dumpvars
xJ
xI
bx H
xG
xF
bx E
0D
b0 C
0B
b0 A
b0 @
0?
b0 >
0=
b0 <
b0 ;
0:
b0 9
08
b0 7
b0 6
05
b0 4
03
b1111111111111111 2
b0 1
bx 0
b0 /
1.
b0 -
0,
b0 +
b0 *
b0 )
0(
0'
0&
b0 %
1$
b0 #
0"
0!
$end
#1
b101 0
#5
b1011000000001011 1
b1011101010111110 6
b1100101011111110 ;
b1010111111111110 @
1,
b1010111111111110110010101111111010111010101111101011000000001011 %
b1010111111111110110010101111111010111010101111101011000000001011 -
b100 *
1(
1&
b1 )
0G
0J
0F
0I
b0 H
0$
#10
0,
1"
1!
1B
1=
18
1D
b1010111111111110 #
b1010111111111110 +
b1010111111111110 C
1?
b1100101011111110 >
b1100101011111110 A
1:
b1011101010111110 9
b1011101010111110 <
b11110 /
15
b1011000000001011 4
b1011000000001011 7
1$
#11
b101 0
#15
b1011111011101111 1
b1101111010101101 6
b1111000000001101 ;
b1100000000000001 @
b1100000000000001111100000000110111011110101011011011111011101111 %
b1100000000000001111100000000110111011110101011011011111011101111 -
0$
b10 )
1G
1J
1F
1I
b1100101011111110 E
b1010111111111110 H
#20
08
b11100 /
05
b1111111111111111 4
b1111111111111111 7
b1011000000001011 9
b1011000000001011 <
b1011101010111110 >
b1011101010111110 A
b1100101011111110 #
b1100101011111110 +
b1100101011111110 C
1$
#21
b101 0
#25
0$
b11 )
b1011101010111110 E
b1100101011111110 H
#30
0=
b1011101010111110 #
b1011101010111110 +
b1011101010111110 C
b1011000000001011 >
b1011000000001011 A
b11000 /
0:
b1111111111111111 9
b1111111111111111 <
1$
#31
b101 0
#35
0$
b100 )
b1011000000001011 E
b1011101010111110 H
#40
1,
0"
0B
b10000 /
0?
b1111111111111111 >
b1111111111111111 A
b1011000000001011 #
b1011000000001011 +
b1011000000001011 C
1$
#41
b101 0
#45
b1000 *
0$
b101 )
0F
0I
b1100000000000001 E
b1011000000001011 H
#50
0,
1"
1B
1=
18
b1100000000000001 #
b1100000000000001 +
b1100000000000001 C
1?
b1111000000001101 >
b1111000000001101 A
1:
b1101111010101101 9
b1101111010101101 <
b11110 /
15
b1011111011101111 4
b1011111011101111 7
1$
#51
b101 0
#55
b1111111011100001 1
b1111101011001110 6
b1111101000010001 ;
b1100000011011110 @
b1100000011011110111110100001000111111010110011101111111011100001 %
b1100000011011110111110100001000111111010110011101111111011100001 -
0(
0$
b110 )
1F
1I
b1111000000001101 E
b1100000000000001 H
#60
08
b11100 /
05
b1111111111111111 4
b1111111111111111 7
b1011111011101111 9
b1011111011101111 <
b1101111010101101 >
b1101111010101101 A
b1111000000001101 #
b1111000000001101 +
b1111000000001101 C
1$
#61
b101 0
#65
0$
b111 )
b1101111010101101 E
b1111000000001101 H
#70
0=
b1101111010101101 #
b1101111010101101 +
b1101111010101101 C
b1011111011101111 >
b1011111011101111 A
b11000 /
0:
b1111111111111111 9
b1111111111111111 <
1$
#71
b101 0
#75
0$
b1000 )
b1011111011101111 E
b1101111010101101 H
#80
0"
0B
b10000 /
0?
b1111111111111111 >
b1111111111111111 A
b1011111011101111 #
b1011111011101111 +
b1011111011101111 C
1$
#81
b101 0
#85
0$
0F
0I
b1100000011011110 E
b1011111011101111 H
#90
0!
b0 /
0D
b1111111111111111 #
b1111111111111111 +
b1111111111111111 C
1$
#91
b101 0
#95
0$
0G
0J
b1111111111111111 E
b1111111111111111 H
#100
1$
#101
b101 0
#105
1"
0.
1'
0$
#110
1$
#111
b101 0
#115
0$
1F
1I
#120
1$
#121
b101 0
#125
1,
0"
1.
0'
b1100 *
1(
0$
b1001 )
#130
0,
1"
1!
1B
1=
18
1D
b1100000011011110 #
b1100000011011110 +
b1100000011011110 C
1?
b1111101000010001 >
b1111101000010001 A
1:
b1111101011001110 9
b1111101011001110 <
b11110 /
15
b1111111011100001 4
b1111111011100001 7
1$
#131
b101 0
#135
b1100110111101111 1
b1000100110101011 6
b100010101100111 ;
b100100011 @
0.
1'
b100100011010001010110011110001001101010111100110111101111 %
b100100011010001010110011110001001101010111100110111101111 -
0(
0$
1G
1J
b1111101000010001 E
b1100000011011110 H
#140
1$
#141
b101 0
#145
0$
b1111111111111111 E
#150
1$
#151
b101 0
#155
1.
0'
1(
0$
b1010 )
#160
08
b11100 /
05
b1111111111111111 4
b1111111111111111 7
b1111111011100001 9
b1111111011100001 <
b1111101011001110 >
b1111101011001110 A
b1111101000010001 #
b1111101000010001 +
b1111101000010001 C
1$
#161
b101 0
#165
0.
1'
0$
b1111101011001110 E
b1111101000010001 H
#170
1$
#171
b101 0
#175
0$
b1111111111111111 E
#180
1$
#181
b101 0
#185
1.
0'
0$
b1011 )
#190
0=
b1111101011001110 #
b1111101011001110 +
b1111101011001110 C
b1111111011100001 >
b1111111011100001 A
b11000 /
0:
b1111111111111111 9
b1111111111111111 <
1$
#191
b101 0
#195
0.
1'
0$
b1111111011100001 E
b1111101011001110 H
#200
1$
#201
b101 0
#205
0$
b1111111111111111 E
#210
1$
#211
b101 0
#215
1.
0'
0$
b1100 )
#220
1,
0"
0B
b10000 /
0?
b1111111111111111 >
b1111111111111111 A
b1111111011100001 #
b1111111011100001 +
b1111111011100001 C
1$
#221
b101 0
#225
b10000 *
0$
b1101 )
0F
0I
b100100011 E
b1111111011100001 H
#230
0,
1"
1B
1=
18
b100100011 #
b100100011 +
b100100011 C
1?
b100010101100111 >
b100010101100111 A
1:
b1000100110101011 9
b1000100110101011 <
b11110 /
15
b1100110111101111 4
b1100110111101111 7
1$
#231
b101 0
#235
b100010001000100 1
b11001100110011 6
b10001000100010 ;
b1000100010001 @
0.
1'
b1000100010001001000100010001000110011001100110100010001000100 %
b1000100010001001000100010001000110011001100110100010001000100 -
0$
1F
1I
b100010101100111 E
b100100011 H
#240
1$
#241
b101 0
#245
0$
b1111111111111111 E
#250
1$
#251
b101 0
#255
1.
0'
0(
0$
b1110 )
#260
08
b11100 /
05
b1111111111111111 4
b1111111111111111 7
b1100110111101111 9
b1100110111101111 <
b1000100110101011 >
b1000100110101011 A
b100010101100111 #
b100010101100111 +
b100010101100111 C
1$
#261
b101 0
#265
0$
b1111 )
b1000100110101011 E
b100010101100111 H
#270
0=
b1000100110101011 #
b1000100110101011 +
b1000100110101011 C
b1100110111101111 >
b1100110111101111 A
b11000 /
0:
b1111111111111111 9
b1111111111111111 <
1$
#271
b101 0
#275
0$
b10000 )
b1100110111101111 E
b1000100110101011 H
#280
0"
0B
b10000 /
0?
b1111111111111111 >
b1111111111111111 A
b1100110111101111 #
b1100110111101111 +
b1100110111101111 C
1$
#281
b101 0
#285
0$
0F
0I
b1000100010001 E
b1100110111101111 H
