ex5/register_stage.v
module register_stage #(parameter WIDTH=32) (input wire clk, input wire res_n,
                                   input wire[WIDTH-1:0] fill_in, input wire[WIDTH-1:0] fwd_in, output reg[WIDTH-1:0] data_out,
                                   input wire shift_in, input wire shift_out,
                                   input wire prev_filled, output reg filled, input wire next_filled
                                  );

	always @(posedge clk or negedge res_n)
	begin
		if (res_n == 1'b0)
		begin
			data_out <= {WIDTH{1'b0}};
			filled <= 1'b0;
		end
		else
		begin
			case({shift_in,shift_out})
				2'b00: // Do nothing
				begin
					data_out <= data_out;
					filled <= filled;
				end
				2'b01: // All register stages shift one forward.
				begin
					data_out <= fwd_in;
					filled <= prev_filled;
				end
				2'b10: // Fill in a new value without shifting.
				begin
					if(prev_filled == 1'b0 && filled == 1'b0 && next_filled == 1'b1)
					begin // Fill in if this stage is the first empty one ...
						data_out <= fill_in;
						filled <= 1'b1;
					end
					else
					begin // ... and keep the old value if either filled, or empty but not the first empty one.
						data_out <= data_out;
						filled <= filled;
					end
				end
				2'b11:
				begin
					if(prev_filled == 1'b0 && filled == 1'b1 && next_filled == 1'b1)
					begin // Fill in if this stage WILL be the first empty one ...
						data_out <= fill_in;
						filled <= 1'b1;
					end
					else
					begin // ... or shift the value
						data_out <= fwd_in;
						filled <= prev_filled;
					end
				end
			endcase
		end
	end
endmodule

ex5/fifo.v
`default_nettype none
module fifo #(parameter WIDTH=32, parameter DEPTH=8) (input wire clk, input wire res_n,
                                                      input wire[WIDTH-1:0] wdata, output wire[WIDTH-1:0] rdata,
                                                      input wire shift_in, input wire shift_out,
                                                      output wire full, output wire empty
                                                     );

wire[WIDTH-1:0] data [DEPTH:0];
wire[DEPTH+1:0] filled;

assign full  = filled[1];
assign empty = !filled[DEPTH];

assign data[0] = {WIDTH{1'b1}}; // For debugging: If there are all ones, they must have come from here...
assign rdata = data[DEPTH];
assign filled[0]       = 1'b0;
assign filled[DEPTH+1] = 1'b1;



generate
	genvar i;
	for(i=0; i<DEPTH; i=i+1)
	begin : foobar
		register_stage #(.WIDTH(WIDTH)) stage_I (.clk(clk), .res_n(res_n),
		                           .fill_in(wdata), .fwd_in(data[i]), .data_out(data[i+1]),
		                           .shift_in(shift_in), .shift_out(shift_out),
		                           .prev_filled(filled[i]), .filled(filled[i+1]), .next_filled(filled[i+2])
		                          );
	end
endgenerate

endmodule

ex5/fifo_tb.v
`default_nettype none
`timescale 10ns/1ns

module fifo_tb;
parameter TESTWIDTH=8;
parameter TESTDEPTH=3;
	//{{{
	/* Make a regular pulsing clock. */
	parameter clk_period=1;
	parameter half_clk_period=clk_period*0.5;
	reg clk = 1;
	always begin
		#half_clk_period
		//$display("clk \\");
		clk = 1'b0;

		#half_clk_period
		$display("clk /");
		clk = 1'b1;
	end
	//}}}




	/* Make a reset that pulses once. */
	reg res_n = 0;

	reg[TESTWIDTH-1:0] indata={TESTWIDTH{1'b0}};
	wire[TESTWIDTH-1:0] outdata;
	reg shift_in;
	reg shift_out;
	wire full;
	wire empty;

	fifo #(.WIDTH(TESTWIDTH), .DEPTH(TESTDEPTH)) fifo_I(.clk(clk), .res_n(res_n),
	                                            .wdata(indata), .rdata(outdata),
	                                            .shift_in(shift_in), .shift_out(shift_out),
	                                            .full(full), .empty(empty)
	                                           );






	initial begin
	$dumpfile("fifo.vcd");
	$dumpvars(0, fifo_tb);
	shift_in  <= 0;
	shift_out <= 0;
	#half_clk_period
	res_n <= 1;
	$display("STARTING NORMAL TEST:");
	shift_in <= 1;
	indata <= 8'h12;
	#clk_period
	shift_in <= 1;
	indata <= 8'h34;
	#clk_period
	shift_in <= 1;
	indata <= 8'h56;
	#clk_period
	shift_in <= 1;
	indata <= 8'h78;
	#clk_period
	shift_in <= 1;
	indata <= 8'h9a;
	#clk_period
	shift_in <= 0;
	shift_out <= 1;
	#clk_period
	#clk_period
	#clk_period
	#clk_period
	#clk_period
	#clk_period
	#clk_period
	#clk_period
	shift_out <= 0;



	#10 $finish;
	end


	always @(outdata, full, empty) begin
		if(full == 1'b0 && empty == 1'b0)
			$display("%t: output=%h",$time, outdata);
		if(full == 1'b0 && empty == 1'b1)
			$display("%t: output=%h EMPTY",$time, outdata);
		if(full == 1'b1 && empty == 1'b0)
			$display("%t: output=%h FULL",$time, outdata);
		if(full == 1'b1 && empty == 1'b1)
			$display("%t: output=%h FULL EMPTY",$time, outdata);
	end





	//initial $monitor("%t: output: %h (%0d)", $time, outdata, value);



endmodule

ex5/fifo.vcd
$date
	Wed Jan 27 19:17:12 2016
$end
$version
	Icarus Verilog
$end
$timescale
	1ns
$end
$scope module fifo_tb $end
$var wire 8 ! outdata [7:0] $end
$var wire 1 " full $end
$var wire 1 # empty $end
$var reg 1 $ clk $end
$var reg 8 % indata [7:0] $end
$var reg 1 & res_n $end
$var reg 1 ' shift_in $end
$var reg 1 ( shift_out $end
$scope module fifo_I $end
$var wire 1 $ clk $end
$var wire 8 ) rdata [7:0] $end
$var wire 1 & res_n $end
$var wire 1 ' shift_in $end
$var wire 1 ( shift_out $end
$var wire 8 * wdata [7:0] $end
$var wire 1 " full $end
$var wire 5 + filled [4:0] $end
$var wire 1 # empty $end
$scope begin foobar[0] $end
$scope module stage_I $end
$var wire 1 $ clk $end
$var wire 8 , fill_in [7:0] $end
$var wire 8 - fwd_in [7:0] $end
$var wire 1 . next_filled $end
$var wire 1 / prev_filled $end
$var wire 1 & res_n $end
$var wire 1 ' shift_in $end
$var wire 1 ( shift_out $end
$var reg 8 0 data_out [7:0] $end
$var reg 1 1 filled $end
$upscope $end
$upscope $end
$scope begin foobar[1] $end
$scope module stage_I $end
$var wire 1 $ clk $end
$var wire 8 2 fill_in [7:0] $end
$var wire 8 3 fwd_in [7:0] $end
$var wire 1 4 next_filled $end
$var wire 1 5 prev_filled $end
$var wire 1 & res_n $end
$var wire 1 ' shift_in $end
$var wire 1 ( shift_out $end
$var reg 8 6 data_out [7:0] $end
$var reg 1 7 filled $end
$upscope $end
$upscope $end
$scope begin foobar[2] $end
$scope module stage_I $end
$var wire 1 $ clk $end
$var wire 8 8 fill_in [7:0] $end
$var wire 8 9 fwd_in [7:0] $end
$var wire 1 : next_filled $end
$var wire 1 ; prev_filled $end
$var wire 1 & res_n $end
$var wire 1 ' shift_in $end
$var wire 1 ( shift_out $end
$var reg 8 < data_out [7:0] $end
$var reg 1 = filled $end
$upscope $end
$upscope $end
$upscope $end
$upscope $end
$enddefinitions $end
#0
$dumpvars
0=
b0 <
0;
1:
b0 9
b0 8
07
b0 6
05
04
b0 3
b0 2
01
b0 0
0/
0.
b11111111 -
b0 ,
b10000 +
b0 *
b0 )
0(
0'
0&
b0 %
1$
1#
0"
b0 !
$end
#5
b10010 %
b10010 *
b10010 ,
b10010 2
b10010 8
1'
1&
0$
#10
0#
14
b11000 +
1=
b10010 !
b10010 )
b10010 <
1$
#15
b110100 %
b110100 *
b110100 ,
b110100 2
b110100 8
0$
#20
1;
1.
b11100 +
17
b110100 6
b110100 9
1$
#25
b1010110 %
b1010110 *
b1010110 ,
b1010110 2
b1010110 8
0$
#30
1"
15
b11110 +
11
b1010110 0
b1010110 3
1$
#35
b1111000 %
b1111000 *
b1111000 ,
b1111000 2
b1111000 8
0$
#40
1$
#45
b10011010 %
b10011010 *
b10011010 ,
b10011010 2
b10011010 8
0$
#50
1$
#55
1(
0'
0$
#60
0"
05
b11100 +
01
b11111111 0
b11111111 3
b1010110 6
b1010110 9
b110100 !
b110100 )
b110100 <
1$
#65
0$
#70
0;
0.
b1010110 !
b1010110 )
b1010110 <
b11000 +
07
b11111111 6
b11111111 9
1$
#75
0$
#80
1#
04
b10000 +
0=
b11111111 !
b11111111 )
b11111111 <
1$
#85
0$
#90
1$
#95
0$
#100
1$
#105
0$
#110
1$
#115
0$
#120
1$
#125
0$
#130
1$
#135
0(
0$
