ex5/register_stage.v
module register_stage #(parameter WIDTH=32) (input wire clk, input wire res_n,
                                   input wire[WIDTH-1:0] fill_in, input wire[WIDTH-1:0] fwd_in, output reg[WIDTH-1:0] data_out,
                                   input wire shift_in, input wire shift_out,
                                   input wire prev_filled, output reg filled, input wire next_filled
                                  );

	always @(posedge clk or negedge res_n)
	begin
		if (res_n == 1'b0)
		begin
			data_out <= {WIDTH{1'b0}};
			filled <= 1'b0;
		end
		else
		begin
			case({shift_in,shift_out})
				2'b00: // Do nothing
				begin
					data_out <= data_out;
					filled <= filled;
				end
				2'b01: // All register stages shift one forward.
				begin
					data_out <= fwd_in;
					filled <= prev_filled;
				end
				2'b10: // Fill in a new value without shifting.
				begin
					if(prev_filled == 1'b0 && filled == 1'b0 && next_filled == 1'b1)
					begin // Fill in if this stage is the first empty one ...
						data_out <= fill_in;
						filled <= 1'b1;
					end
					else
					begin // ... and keep the old value if either filled, or empty but not the first empty one.
						data_out <= data_out;
						filled <= filled;
					end
				end
				2'b11:
				begin
					if(prev_filled == 1'b0 && filled == 1'b1 && next_filled == 1'b1)
					begin // Fill in if this stage WILL be the first empty one ...
						data_out <= fill_in;
						filled <= 1'b1;
					end
					else
					begin // ... or shift the value
						data_out <= fwd_in;
						filled <= prev_filled;
					end
				end
			endcase
		end
	end
endmodule

ex5/fifo.v
`default_nettype none
module fifo #(parameter WIDTH=32, parameter DEPTH=8) (input wire clk, input wire res_n,
                                                      input wire[WIDTH-1:0] wdata, output wire[WIDTH-1:0] rdata,
                                                      input wire shift_in, input wire shift_out,
                                                      output wire full, output wire empty
                                                     );

wire[WIDTH-1:0] data [DEPTH:0];
wire[DEPTH+1:0] filled;

assign full  = filled[1];
assign empty = !filled[DEPTH];

assign data[0] = {WIDTH{1'b1}}; // For debugging: If there are all ones, they must have come from here...
assign rdata = data[DEPTH];
assign filled[0]       = 1'b0;
assign filled[DEPTH+1] = 1'b1;

generate
	genvar i;
	for(i=0; i<DEPTH; i=i+1)
	begin : foobar
		//$display("asdf");
		register_stage #(.WIDTH(WIDTH)) stage_I (.clk(clk), .res_n(res_n),
		                           .fill_in(wdata), .fwd_in(data[i]), .data_out(data[i+1]),
		                           .shift_in(shift_in), .shift_out(shift_out),
		                           .prev_filled(filled[i]), .filled(filled[i+1]), .next_filled(filled[i+2])
		                          );
	end
endgenerate


`ifdef DEBUG
always @(posedge clk)
begin
	if(full == 1'b1 && shift_in == 1'b1)

		$display("%c[1;31m%m: Dropping 0x%h, because the FIFO is full.%c[0m", 27, wdata, 27);
	if(empty == 1'b1 && shift_out == 1'b1)
		$display("%c[1;31m%m: Returning invalid value due to readout of empty FIFO.%c[0m", 27, 27);
end
`endif

`ifdef VERBOSE

integer j;
always @(posedge clk)
begin
	$write("%c[1;34m%m: STATUS:", 27);
	if(shift_in == 1'b1)
		$write(" => %h ", wdata);
	else
		$write(" -> %h ", wdata);
	for (j = 1; j != DEPTH+1; j = j + 1)
	begin
		if(filled[j] == 1'b1)
			$write("■");
		else
			$write("◻");
	end
	if(shift_out == 1'b1)
		$write(" => %h", rdata);
	else
		$write(" -> %h", rdata);
	if(full == 1'b1)
		$write(" FULL");
	if(empty == 1'b1)
		$write(" EMPTY");
	if(res_n == 1'b0)
		$write(" RESET");
	$display("%c[0m", 27);
end
`endif

endmodule

ex5/fifo_tb.v
		//$write(" ◻◼▯■□●◯◾◾◽ Address = %g",j);
`default_nettype none
`timescale 10ns/1ns

module fifo_tb;
parameter TESTWIDTH=8;
parameter TESTDEPTH=10;
	//{{{
	/* Make a regular pulsing clock. */
	parameter clk_period=1;
	parameter half_clk_period=clk_period*0.5;
	reg clk = 1;
	always begin
		#half_clk_period
		//$display("clk \\");
		clk = 1'b0;

		#half_clk_period
		$display("clk /");
		clk = 1'b1;
	end
	//}}}




	/* Make a reset that pulses once. */
	reg res_n = 0;

	reg[TESTWIDTH-1:0] indata={TESTWIDTH{1'b0}};
	wire[TESTWIDTH-1:0] outdata;
	reg shift_in;
	reg shift_out;
	wire full;
	wire empty;

	fifo #(.WIDTH(TESTWIDTH), .DEPTH(TESTDEPTH)) fifo_I(.clk(clk), .res_n(res_n),
	                                            .wdata(indata), .rdata(outdata),
	                                            .shift_in(shift_in), .shift_out(shift_out),
	                                            .full(full), .empty(empty)
	                                           );

//	task print_status(input[TESTWIDTH-1:0] outdata, input full, input empty);
//	begin
//		if(full == 1'b0 && empty == 1'b0)
//			$display("%t: output=%h",$time, outdata);
//		if(full == 1'b0 && empty == 1'b1)
//			$display("%t: output=%h EMPTY",$time, outdata);
//		if(full == 1'b1 && empty == 1'b0)
//			$display("%t: output=%h FULL",$time, outdata);
//		if(full == 1'b1 && empty == 1'b1)
//			$display("%t: output=%h FULL EMPTY",$time, outdata);
//	end
//	endtask
//	always @(outdata, full, empty) begin
//		print_status(outdata, full, empty);
//	end



// Jeweils alle Kombinationen von shift_in, shift_out und reset für die Füllstände "Leer" "Ein Element" "Halbvoll" "Fast voll" und "Voll".
// Für echte Hardware zusätzlich noch Test, ob der Fifo bei bestimmten Daten Probleme bekommt (Siehe FDIV-Bug).

reg[TESTWIDTH-1:0][4:0] TESTVECTOR = {8'haf, 8'hfe, 8'ha5, 8'h31};

	initial begin
	$dumpfile("fifo.vcd");
	$dumpvars(0, fifo_tb);
	shift_in  <= 0;
	shift_out <= 0;
	#half_clk_period
	res_n <= 1;
	$display("STARTING NORMAL TEST:");
	shift_in <= 1;
	indata <= 8'h12;
	#clk_period
	shift_in <= 1;
	indata <= 8'h34;
	#clk_period
	shift_in <= 1;
	indata <= 8'h56;
	#clk_period
	shift_in <= 1;
	indata <= 8'h78;
	#clk_period
	shift_in <= 1;
	indata <= 8'h9a;
	#clk_period
	shift_in <= 0;
	shift_out <= 1;
	#clk_period
	#clk_period
	#clk_period
	#clk_period
	#clk_period
	#clk_period
	#clk_period
	#clk_period
	shift_out <= 0;



	#10 $finish;
	end







	//initial $monitor("%t: output: %h (%0d)", $time, outdata, value);



endmodule

ex5/fifo.vcd
$date
	Sun Jan 31 12:49:23 2016
$end
$version
	Icarus Verilog
$end
$timescale
	1ns
$end
$scope module fifo_tb $end
$var wire 8 ! outdata [7:0] $end
$var wire 1 " full $end
$var wire 1 # empty $end
$var reg 40 $ TESTVECTOR [39:0] $end
$var reg 1 % clk $end
$var reg 8 & indata [7:0] $end
$var reg 1 ' res_n $end
$var reg 1 ( shift_in $end
$var reg 1 ) shift_out $end
$scope module fifo_I $end
$var wire 1 % clk $end
$var wire 8 * rdata [7:0] $end
$var wire 1 ' res_n $end
$var wire 1 ( shift_in $end
$var wire 1 ) shift_out $end
$var wire 8 + wdata [7:0] $end
$var wire 1 " full $end
$var wire 12 , filled [11:0] $end
$var wire 1 # empty $end
$var integer 32 - j [31:0] $end
$scope begin foobar[0] $end
$scope module stage_I $end
$var wire 1 % clk $end
$var wire 8 . fill_in [7:0] $end
$var wire 8 / fwd_in [7:0] $end
$var wire 1 0 next_filled $end
$var wire 1 1 prev_filled $end
$var wire 1 ' res_n $end
$var wire 1 ( shift_in $end
$var wire 1 ) shift_out $end
$var reg 8 2 data_out [7:0] $end
$var reg 1 3 filled $end
$upscope $end
$upscope $end
$scope begin foobar[1] $end
$scope module stage_I $end
$var wire 1 % clk $end
$var wire 8 4 fill_in [7:0] $end
$var wire 8 5 fwd_in [7:0] $end
$var wire 1 6 next_filled $end
$var wire 1 7 prev_filled $end
$var wire 1 ' res_n $end
$var wire 1 ( shift_in $end
$var wire 1 ) shift_out $end
$var reg 8 8 data_out [7:0] $end
$var reg 1 9 filled $end
$upscope $end
$upscope $end
$scope begin foobar[2] $end
$scope module stage_I $end
$var wire 1 % clk $end
$var wire 8 : fill_in [7:0] $end
$var wire 8 ; fwd_in [7:0] $end
$var wire 1 < next_filled $end
$var wire 1 = prev_filled $end
$var wire 1 ' res_n $end
$var wire 1 ( shift_in $end
$var wire 1 ) shift_out $end
$var reg 8 > data_out [7:0] $end
$var reg 1 ? filled $end
$upscope $end
$upscope $end
$scope begin foobar[3] $end
$scope module stage_I $end
$var wire 1 % clk $end
$var wire 8 @ fill_in [7:0] $end
$var wire 8 A fwd_in [7:0] $end
$var wire 1 B next_filled $end
$var wire 1 C prev_filled $end
$var wire 1 ' res_n $end
$var wire 1 ( shift_in $end
$var wire 1 ) shift_out $end
$var reg 8 D data_out [7:0] $end
$var reg 1 E filled $end
$upscope $end
$upscope $end
$scope begin foobar[4] $end
$scope module stage_I $end
$var wire 1 % clk $end
$var wire 8 F fill_in [7:0] $end
$var wire 8 G fwd_in [7:0] $end
$var wire 1 H next_filled $end
$var wire 1 I prev_filled $end
$var wire 1 ' res_n $end
$var wire 1 ( shift_in $end
$var wire 1 ) shift_out $end
$var reg 8 J data_out [7:0] $end
$var reg 1 K filled $end
$upscope $end
$upscope $end
$scope begin foobar[5] $end
$scope module stage_I $end
$var wire 1 % clk $end
$var wire 8 L fill_in [7:0] $end
$var wire 8 M fwd_in [7:0] $end
$var wire 1 N next_filled $end
$var wire 1 O prev_filled $end
$var wire 1 ' res_n $end
$var wire 1 ( shift_in $end
$var wire 1 ) shift_out $end
$var reg 8 P data_out [7:0] $end
$var reg 1 Q filled $end
$upscope $end
$upscope $end
$scope begin foobar[6] $end
$scope module stage_I $end
$var wire 1 % clk $end
$var wire 8 R fill_in [7:0] $end
$var wire 8 S fwd_in [7:0] $end
$var wire 1 T next_filled $end
$var wire 1 U prev_filled $end
$var wire 1 ' res_n $end
$var wire 1 ( shift_in $end
$var wire 1 ) shift_out $end
$var reg 8 V data_out [7:0] $end
$var reg 1 W filled $end
$upscope $end
$upscope $end
$scope begin foobar[7] $end
$scope module stage_I $end
$var wire 1 % clk $end
$var wire 8 X fill_in [7:0] $end
$var wire 8 Y fwd_in [7:0] $end
$var wire 1 Z next_filled $end
$var wire 1 [ prev_filled $end
$var wire 1 ' res_n $end
$var wire 1 ( shift_in $end
$var wire 1 ) shift_out $end
$var reg 8 \ data_out [7:0] $end
$var reg 1 ] filled $end
$upscope $end
$upscope $end
$scope begin foobar[8] $end
$scope module stage_I $end
$var wire 1 % clk $end
$var wire 8 ^ fill_in [7:0] $end
$var wire 8 _ fwd_in [7:0] $end
$var wire 1 ` next_filled $end
$var wire 1 a prev_filled $end
$var wire 1 ' res_n $end
$var wire 1 ( shift_in $end
$var wire 1 ) shift_out $end
$var reg 8 b data_out [7:0] $end
$var reg 1 c filled $end
$upscope $end
$upscope $end
$scope begin foobar[9] $end
$scope module stage_I $end
$var wire 1 % clk $end
$var wire 8 d fill_in [7:0] $end
$var wire 8 e fwd_in [7:0] $end
$var wire 1 f next_filled $end
$var wire 1 g prev_filled $end
$var wire 1 ' res_n $end
$var wire 1 ( shift_in $end
$var wire 1 ) shift_out $end
$var reg 8 h data_out [7:0] $end
$var reg 1 i filled $end
$upscope $end
$upscope $end
$upscope $end
$upscope $end
$enddefinitions $end
#0
$dumpvars
0i
b0 h
0g
1f
b0 e
b0 d
0c
b0 b
0a
0`
b0 _
b0 ^
0]
b0 \
0[
0Z
b0 Y
b0 X
0W
b0 V
0U
0T
b0 S
b0 R
0Q
b0 P
0O
0N
b0 M
b0 L
0K
b0 J
0I
0H
b0 G
b0 F
0E
b0 D
0C
0B
b0 A
b0 @
0?
b0 >
0=
0<
b0 ;
b0 :
09
b0 8
07
06
b0 5
b0 4
03
b0 2
01
00
b11111111 /
b0 .
b1011 -
b100000000000 ,
b0 +
b0 *
0)
0(
0'
b0 &
1%
b10101111111111101010010100110001 $
1#
0"
b0 !
$end
#5
b10010 &
b10010 +
b10010 .
b10010 4
b10010 :
b10010 @
b10010 F
b10010 L
b10010 R
b10010 X
b10010 ^
b10010 d
1(
1'
0%
#10
0#
1`
b110000000000 ,
1i
b10010 !
b10010 *
b10010 h
b1011 -
1%
#15
b110100 &
b110100 +
b110100 .
b110100 4
b110100 :
b110100 @
b110100 F
b110100 L
b110100 R
b110100 X
b110100 ^
b110100 d
0%
#20
1g
1Z
b111000000000 ,
1c
b110100 b
b110100 e
b1011 -
1%
#25
b1010110 &
b1010110 +
b1010110 .
b1010110 4
b1010110 :
b1010110 @
b1010110 F
b1010110 L
b1010110 R
b1010110 X
b1010110 ^
b1010110 d
0%
#30
1a
1T
b111100000000 ,
1]
b1010110 \
b1010110 _
b1011 -
1%
#35
b1111000 &
b1111000 +
b1111000 .
b1111000 4
b1111000 :
b1111000 @
b1111000 F
b1111000 L
b1111000 R
b1111000 X
b1111000 ^
b1111000 d
0%
#40
1[
1N
b111110000000 ,
1W
b1111000 V
b1111000 Y
b1011 -
1%
#45
b10011010 &
b10011010 +
b10011010 .
b10011010 4
b10011010 :
b10011010 @
b10011010 F
b10011010 L
b10011010 R
b10011010 X
b10011010 ^
b10011010 d
0%
#50
1U
1H
b111111000000 ,
1Q
b10011010 P
b10011010 S
b1011 -
1%
#55
1)
0(
0%
#60
0U
0H
b11111111 2
b11111111 5
b111110000000 ,
0Q
b0 P
b0 S
b10011010 V
b10011010 Y
b1111000 \
b1111000 _
b1010110 b
b1010110 e
b110100 !
b110100 *
b110100 h
b1011 -
1%
#65
0%
#70
0[
0N
b1010110 !
b1010110 *
b1010110 h
b1111000 b
b1111000 e
b10011010 \
b10011010 _
b111100000000 ,
0W
b0 V
b0 Y
b11111111 8
b11111111 ;
b1011 -
1%
#75
0%
#80
0a
0T
b11111111 >
b11111111 A
b111000000000 ,
0]
b0 \
b0 _
b10011010 b
b10011010 e
b1111000 !
b1111000 *
b1111000 h
b1011 -
1%
#85
0%
#90
0g
0Z
b10011010 !
b10011010 *
b10011010 h
b110000000000 ,
0c
b0 b
b0 e
b11111111 D
b11111111 G
b1011 -
1%
#95
0%
#100
1#
0`
b11111111 J
b11111111 M
b100000000000 ,
0i
b0 !
b0 *
b0 h
b1011 -
1%
#105
0%
#110
b11111111 P
b11111111 S
b1011 -
1%
#115
0%
#120
b11111111 V
b11111111 Y
b1011 -
1%
#125
0%
#130
b11111111 \
b11111111 _
b1011 -
1%
#135
0)
0%
#140
b1011 -
1%
#145
0%
#150
b1011 -
1%
#155
0%
#160
b1011 -
1%
#165
0%
#170
b1011 -
1%
#175
0%
#180
b1011 -
1%
#185
0%
#190
b1011 -
1%
#195
0%
#200
b1011 -
1%
#205
0%
#210
b1011 -
1%
#215
0%
#220
b1011 -
1%
#225
0%
#230
b1011 -
1%
