ex5/register_stage.v
module register_stage #(parameter WIDTH=32) (input wire clk, input wire res_n,
                                   input wire[WIDTH-1:0] fill_in, input wire[WIDTH-1:0] fwd_in, output reg[WIDTH-1:0] data_out,
                                   input wire shift_in, input wire shift_out,
                                   input wire prev_filled, output reg filled, input wire next_filled
                                  );

	always @(posedge clk or negedge res_n)
	begin
		if (res_n == 1'b0)
		begin
			data_out <= {WIDTH{1'b0}};
			filled <= 1'b0;
		end
		else
		begin
			case({shift_in,shift_out})
				2'b00: // Do nothing
				begin
					data_out <= data_out;
					filled <= filled;
				end
				2'b01: // All register stages shift one forward.
				begin
					data_out <= fwd_in;
					filled <= prev_filled;
				end
				2'b10: // Fill in a new value without shifting.
				begin
					if(prev_filled == 1'b0 && filled == 1'b0 && next_filled == 1'b1)
					begin // Fill in if this stage is the first empty one ...
						data_out <= fill_in;
						filled <= 1'b1;
					end
					else
					begin // ... and keep the old value if either filled, or empty but not the first empty one.
						data_out <= data_out;
						filled <= filled;
					end
				end
				2'b11:
				begin
					if(prev_filled == 1'b0 && filled == 1'b1 && next_filled == 1'b1)
					begin // Fill in if this stage WILL be the first empty one ...
						data_out <= fill_in;
						filled <= 1'b1;
					end
					else
					begin // ... or shift the value
						data_out <= fwd_in;
						filled <= prev_filled;
					end
				end
			endcase
		end
	end
endmodule

ex5/fifo.v
`default_nettype none
module fifo #(parameter WIDTH=32, parameter DEPTH=8) (input wire clk, input wire res_n,
                                                      input wire[WIDTH-1:0] wdata, output wire[WIDTH-1:0] rdata,
                                                      input wire shift_in, input wire shift_out,
                                                      output wire full, output wire empty
                                                     );

wire[WIDTH-1:0] data [DEPTH:0];
wire[DEPTH+1:0] filled;

assign full  = filled[1];
assign empty = !filled[DEPTH];

`ifdef DEBUG
assign data[0] = {WIDTH{1'b1}}; // For debugging: If there are all ones, they must have come from here...
`else
assign data[0] = {WIDTH{1'b0}}; // ... in normal operation, zeros are more common.
`endif
assign rdata = data[DEPTH];
assign filled[0]       = 1'b0;
assign filled[DEPTH+1] = 1'b1;

generate
	genvar i;
	for(i=0; i<DEPTH; i=i+1)
	begin : foobar
		//$display("asdf");
		register_stage #(.WIDTH(WIDTH)) stage_I (.clk(clk), .res_n(res_n),
		                                         .fill_in(wdata), .fwd_in(data[i]), .data_out(data[i+1]),
		                                         .shift_in(shift_in), .shift_out(shift_out),
		                                         .prev_filled(filled[i]), .filled(filled[i+1]), .next_filled(filled[i+2])
		                                        );
	end
endgenerate


`ifdef DEBUG
always @(posedge clk)
begin
	if(full == 1'b1 && shift_in == 1'b1 && res_n == 1'b1)
		$display("%c[1;33m%m: Dropping 0x%h, because the FIFO is full.%c[0m", 27, wdata, 27);
	if(empty == 1'b1 && shift_out == 1'b1 && res_n == 1'b1)
		$display("%c[1;33m%m: Returning invalid value due to readout of empty FIFO.%c[0m", 27, 27);
	if(res_n == 1'b0 && (shift_in == 1'b1 || shift_out == 1'b1))
		$display("%c[1;33m%m: Trying to access FIFO while it is in reset.%c[0m", 27, 27);
end
`endif

`ifdef VERBOSE
integer j;
always @(posedge clk)
begin
	#1
	$write("%c[1;34m%m: STATUS:", 27);
	if(shift_in == 1'b1)
		$write(" => %h ", wdata);
	else
		$write(" -> %h ", wdata);
	for (j = 1; j != DEPTH+1; j = j + 1)
	begin
		if(filled[j] == 1'b1)
			$write("■");
		else
			$write("◻");
	end
	if(shift_out == 1'b1)
		$write(" => %h", rdata);
	else
		$write(" -> %h", rdata);
	if(full == 1'b1)
		$write(" FULL");
	if(empty == 1'b1)
		$write(" EMPTY");
	if(res_n == 1'b0)
		$write(" RESET");
	$display("%c[0m", 27);
end
`endif

endmodule

ex5/fifo_tb.v
		//$write(" ◻◼▯■□●◯◾◾◽ Address = %g",j);
`default_nettype none
`timescale 1ns/1ns

module fifo_tb;
parameter TESTWIDTH=16;
parameter TESTDEPTH=10;
	//{{{
	/* Make a regular pulsing clock. */
	parameter clk_period=10;
	parameter half_clk_period=5;
	//parameter half_clk_period=clk_period*0.5;
	reg clk = 1;
	always begin
		#half_clk_period
		//$display("clk \\");
		clk = 1'b0;

		#half_clk_period
		`ifdef SHOWCLOCK
			$display("clk /");
		`endif
		clk = 1'b1;
	end
	//}}}




	/* Make a reset that pulses once. */
	reg res_n = 0;

	reg[TESTWIDTH-1:0] indata={TESTWIDTH{1'b0}};
	wire[TESTWIDTH-1:0] outdata;
	reg shift_in;
	reg shift_out;
	wire full;
	wire empty;

	fifo #(.WIDTH(TESTWIDTH), .DEPTH(TESTDEPTH)) fifo_I(.clk(clk), .res_n(res_n),
	                                            .wdata(indata), .rdata(outdata),
	                                            .shift_in(shift_in), .shift_out(shift_out),
	                                            .full(full), .empty(empty)
	                                           );

//	task print_status(input[TESTWIDTH-1:0] outdata, input full, input empty);
//	begin
//		if(full == 1'b0 && empty == 1'b0)
//			$display("%t: output=%h",$time, outdata);
//		if(full == 1'b0 && empty == 1'b1)
//			$display("%t: output=%h EMPTY",$time, outdata);
//		if(full == 1'b1 && empty == 1'b0)
//			$display("%t: output=%h FULL",$time, outdata);
//		if(full == 1'b1 && empty == 1'b1)
//			$display("%t: output=%h FULL EMPTY",$time, outdata);
//	end
//	endtask
//	always @(outdata, full, empty) begin
//		print_status(outdata, full, empty);
//	end



//{{{ Messages, pretty printed

	task pass;
	begin
		$display("%c[1;34m",27);
		$display("***************************************");
		$display("*********** TEST CASE PASS ************");
		$display("***************************************");
		$write("%c[0m",27);
	end
	endtask

	task fail;
	begin
		$display("%c[1;31m",27);
		$display("***************************************");
		$display("*********** TEST CASE FAIL ************");
		$display("***************************************");
		$display("%c[0m",27);
		`ifdef FAILABORT
			$finish;
		`endif
	end
	endtask

	task success;
	begin
			$display("%c[1;32m-----------------------------------------------------------> SUCCESS.%c[0m", 27, 27);
	end
	endtask

	task defeat;
	begin
			$display("%c[1;31m-----------------------------------------------------------> FAILED.%c[0m", 27, 27);
			fail;
	end
	endtask
//}}}



	task check_fifo(input shift_out, input[TESTWIDTH-1:0] outdata, input full, input empty, input[TESTWIDTH-1:0] expected_outdata, input expected_full, input expected_empty);
	begin
		if(full === 1'b1 && empty === 1'b1)
		begin
			$display("%c[1;31mFIFO TEST: EMPTY and FULL at the same time.%c[0m", 27, 27);
			defeat;
		end
		if(full !== expected_full)
		begin
			$display("%c[1;31mFIFO TEST: Expected full = %b but got %b.%c[0m", 27, expected_full, full, 27);
			defeat;
		end
		if(empty !== expected_empty)
		begin
			$display("%c[1;31mFIFO TEST: Expected empty = %b but got %b.%c[0m", 27, expected_empty, empty, 27);
			defeat;
		end
		if(^expected_outdata!==1'bX && expected_empty == 1'b0 && shift_out == 1'b1 && outdata !== expected_outdata)
		begin
			$display("%c[1;31mFIFO TEST: Expected output = %h but got %h.%c[0m", 27, expected_outdata, outdata, 27);
			defeat;
		end
	end
	endtask







// Jeweils alle Kombinationen von shift_in, shift_out und reset für die Füllstände "Leer" "Ein Element" "Halbvoll" "Fast voll" und "Voll".
// Für echte Hardware zusätzlich noch Test, ob der Fifo bei bestimmten Daten Probleme bekommt (Siehe FDIV-Bug).


reg[TESTWIDTH-1:0] TESTVECTOR[TESTDEPTH*2+5:0];

integer write=-1;
integer read=0;
integer i=0;
	initial begin
	$dumpfile("fifo.vcd");
	$dumpvars(0, fifo_tb);
	TESTVECTOR[ 0] = 16'haffe;
	TESTVECTOR[ 1] = 16'hcafe;
	TESTVECTOR[ 2] = 16'hbabe;
	TESTVECTOR[ 3] = 16'hb00b;
	TESTVECTOR[ 4] = 16'hc001;
	TESTVECTOR[ 5] = 16'hf00d;
	TESTVECTOR[ 6] = 16'hdead;
	TESTVECTOR[ 7] = 16'hbeef;
	TESTVECTOR[ 8] = 16'hc0de;
	TESTVECTOR[ 9] = 16'hfa11;
	TESTVECTOR[10] = 16'hface;
	TESTVECTOR[11] = 16'hfee1;
	TESTVECTOR[12] = 16'h0123;
	TESTVECTOR[13] = 16'h4567;
	TESTVECTOR[14] = 16'h89ab;
	TESTVECTOR[15] = 16'hcdef;
	TESTVECTOR[16] = 16'h1111;
	TESTVECTOR[17] = 16'h2222;
	TESTVECTOR[18] = 16'h3333;
	TESTVECTOR[19] = 16'h4444;
	TESTVECTOR[20] = 16'h5555;
	TESTVECTOR[21] = 16'h6666;
	TESTVECTOR[22] = 16'h7777;
	TESTVECTOR[23] = 16'h8888;
	TESTVECTOR[24] = 16'h9999;
	TESTVECTOR[25] = 16'ha5a5;

	shift_in  <= 1'b0;
	shift_out <= 1'b0;
	indata <= {TESTWIDTH{1'b0}};
	#half_clk_period
	res_n <= 1;

	$display("STARTING Shift_in TEST:");
	check_fifo(shift_out, outdata, full, empty, 16'hxxxx, 0, 1);

	repeat(TESTDEPTH-1)
	begin
		shift_in = 1; write++;
		indata <= TESTVECTOR[write][TESTWIDTH-1:0];
		shift_out <= 0;// read++;
		#clk_period;
		check_fifo(shift_out, outdata, full, empty, TESTVECTOR[read][TESTWIDTH-1:0], 0, 0);
	end
	shift_in = 1; write++;
	indata <= TESTVECTOR[write][TESTWIDTH-1:0];
	shift_out <= 0;// read++;
	#clk_period;
	check_fifo(shift_out, outdata, full, empty, TESTVECTOR[read][TESTWIDTH-1:0], 1, 0);

	// NOP to see the full state shown
	shift_in = 0; //write++;
	indata <= TESTVECTOR[write][TESTWIDTH-1:0];
	shift_out <= 0;// read++;
	#clk_period;
	check_fifo(shift_out, outdata, full, empty, TESTVECTOR[read][TESTWIDTH-1:0], 1, 0);
	success;

	$display("STARTING FULL NOP TEST:");
	repeat(5)
	begin
		shift_in = 0; //write++;
		indata <= TESTVECTOR[write][TESTWIDTH-1:0];
		shift_out <= 0;// read++;
		#clk_period;
		check_fifo(shift_out, outdata, full, empty, TESTVECTOR[read][TESTWIDTH-1:0], 1, 0);
	end
	success;

	$display("STARTING Shift_out TEST:");
	repeat(TESTDEPTH-1)
	begin
		shift_in = 0; //write++;
		indata <= TESTVECTOR[write][TESTWIDTH-1:0];
		shift_out <= 1; read++;
		#clk_period;
		check_fifo(shift_out, outdata, full, empty, TESTVECTOR[read][TESTWIDTH-1:0], 0, 0);
	end
	shift_in = 0; //write++;
	indata <= TESTVECTOR[write][TESTWIDTH-1:0];
	shift_out <= 1; read++;
	#clk_period;
	check_fifo(shift_out, outdata, full, empty, TESTVECTOR[read][TESTWIDTH-1:0], 0, 1);

	// NOP to see the empty state shown
	shift_in = 0; //write++;
	indata <= TESTVECTOR[write][TESTWIDTH-1:0];
	shift_out <= 0; //read++;
	#clk_period;
	check_fifo(shift_out, outdata, full, empty, TESTVECTOR[read][TESTWIDTH-1:0], 0, 1);
	success;

	$display("STARTING EMPTY NOP TEST:");
	repeat(5)
	begin
		shift_in = 0; //write++;
		indata <= TESTVECTOR[write][TESTWIDTH-1:0];
		shift_out <= 0;// read++;
		#clk_period;
		check_fifo(shift_out, outdata, full, empty, 16'hxxxx, 0, 1);
	end
	success;

	$display("STARTING UNDERFILL TEST:");
	// FIFO is empty now
	`ifdef DEBUG
		$display("%c[1;33mThere should be 5 debug message here, each saying that invalid data from an empty FIFO is returned.%c[0m", 27, 27);
	`endif
	repeat(5)
	begin
		shift_in = 0; //write++;
		indata <= TESTVECTOR[write][TESTWIDTH-1:0];
		shift_out <= 1;// read++;
		#clk_period;
		check_fifo(shift_out, outdata, full, empty, {TESTWIDTH{1'bx}}, 0, 1); // Only check that the FIFO stays empty
	end
	success;

	$display("STARTING OVERFILL TEST:");
	write=-1;
	read=0;
	check_fifo(shift_out, outdata, full, empty, {TESTWIDTH{1'bx}}, 0, 1);

	repeat(TESTDEPTH-1)
	begin
		shift_in = 1; write++;
		indata <= TESTVECTOR[write][TESTWIDTH-1:0];
		shift_out <= 0;// read++;
		#clk_period;
		check_fifo(shift_out, outdata, full, empty, TESTVECTOR[read][TESTWIDTH-1:0], 0, 0);
	end
	shift_in = 1; write++;
	indata <= TESTVECTOR[write][TESTWIDTH-1:0];
	shift_out <= 0;// read++;
	#clk_period;
	check_fifo(shift_out, outdata, full, empty, TESTVECTOR[read][TESTWIDTH-1:0], 1, 0);

	// FIFO is full now

	`ifdef DEBUG
		$display("%c[1;33mThere should be 5 debug message here, each saying that a data member was dropped.%c[0m", 27, 27);
	`endif
	repeat(5)
	begin
		shift_in = 1; //write++;
		indata <= TESTVECTOR[write][TESTWIDTH-1:0];
		shift_out <= 0;// read++;
		#clk_period;
		check_fifo(shift_out, outdata, full, empty, TESTVECTOR[read][TESTWIDTH-1:0], 1, 0);
	end

	repeat(TESTDEPTH-1)
	begin
		shift_in = 0; //write++;
		indata <= TESTVECTOR[write][TESTWIDTH-1:0];
		shift_out <= 1; read++;
		#clk_period;
		check_fifo(shift_out, outdata, full, empty, TESTVECTOR[read][TESTWIDTH-1:0], 0, 0);
	end
	shift_in = 0; //write++;
	indata <= TESTVECTOR[write][TESTWIDTH-1:0];
	shift_out <= 1; read++;
	#clk_period;
	check_fifo(shift_out, outdata, full, empty, TESTVECTOR[read][TESTWIDTH-1:0], 0, 1);

	// NOP to see the empty state shown
	shift_in = 0; //write++;
	indata <= TESTVECTOR[write][TESTWIDTH-1:0];
	shift_out <= 0; //read++;
	#clk_period;
	check_fifo(shift_out, outdata, full, empty, TESTVECTOR[read][TESTWIDTH-1:0], 0, 1);
	success;


	$display("STARTING EMPTY RESET TEST:");
	write=-1; // Restart the test pattern
	read=0;

	#2 res_n = 0; // Generate a short (asynchronous) spike on the reset line
	#1 res_n = 1;


	check_fifo(shift_out, outdata, full, empty, {TESTWIDTH{1'b0}}, 0, 1);
	shift_in = 0; //write++;
	indata <= TESTVECTOR[write][TESTWIDTH-1:0];
	shift_out <= 0; //read++;
	#clk_period;
	check_fifo(shift_out, outdata, full, empty, {TESTWIDTH{1'b0}}, 0, 1);
	success;





	// TODO:
	// - Reset-test for semi-full
	// - Reset-test for full
	// - Reset-operation-test for empty
	// - Reset-operation-test for semi-full
	// - Reset-operation-test for full
	// - Pass-through-test for empty state
	// - Pass-through-test for semi-full





	//#10
	$finish;
	end







	//initial $monitor("%t: output: %h (%0d)", $time, outdata, value);



endmodule

ex5/fifo.vcd
$date
	Wed Feb  3 14:34:13 2016
$end
$version
	Icarus Verilog
$end
$timescale
	1s
$end
$scope module fifo_tb $end
$var wire 16 ! outdata [15:0] $end
$var wire 1 " full $end
$var wire 1 # empty $end
$var reg 1 $ clk $end
$var reg 16 % indata [15:0] $end
$var reg 1 & res_n $end
$var reg 1 ' shift_in $end
$var reg 1 ( shift_out $end
$var integer 32 ) read [31:0] $end
$var integer 32 * write [31:0] $end
$scope module fifo_I $end
$var wire 1 $ clk $end
$var wire 16 + rdata [15:0] $end
$var wire 1 & res_n $end
$var wire 1 ' shift_in $end
$var wire 1 ( shift_out $end
$var wire 16 , wdata [15:0] $end
$var wire 1 " full $end
$var wire 12 - filled [11:0] $end
$var wire 1 # empty $end
$var integer 32 . j [31:0] $end
$scope begin foobar[0] $end
$scope module stage_I $end
$var wire 1 $ clk $end
$var wire 16 / fill_in [15:0] $end
$var wire 16 0 fwd_in [15:0] $end
$var wire 1 1 next_filled $end
$var wire 1 2 prev_filled $end
$var wire 1 & res_n $end
$var wire 1 ' shift_in $end
$var wire 1 ( shift_out $end
$var reg 16 3 data_out [15:0] $end
$var reg 1 4 filled $end
$upscope $end
$upscope $end
$scope begin foobar[1] $end
$scope module stage_I $end
$var wire 1 $ clk $end
$var wire 16 5 fill_in [15:0] $end
$var wire 16 6 fwd_in [15:0] $end
$var wire 1 7 next_filled $end
$var wire 1 8 prev_filled $end
$var wire 1 & res_n $end
$var wire 1 ' shift_in $end
$var wire 1 ( shift_out $end
$var reg 16 9 data_out [15:0] $end
$var reg 1 : filled $end
$upscope $end
$upscope $end
$scope begin foobar[2] $end
$scope module stage_I $end
$var wire 1 $ clk $end
$var wire 16 ; fill_in [15:0] $end
$var wire 16 < fwd_in [15:0] $end
$var wire 1 = next_filled $end
$var wire 1 > prev_filled $end
$var wire 1 & res_n $end
$var wire 1 ' shift_in $end
$var wire 1 ( shift_out $end
$var reg 16 ? data_out [15:0] $end
$var reg 1 @ filled $end
$upscope $end
$upscope $end
$scope begin foobar[3] $end
$scope module stage_I $end
$var wire 1 $ clk $end
$var wire 16 A fill_in [15:0] $end
$var wire 16 B fwd_in [15:0] $end
$var wire 1 C next_filled $end
$var wire 1 D prev_filled $end
$var wire 1 & res_n $end
$var wire 1 ' shift_in $end
$var wire 1 ( shift_out $end
$var reg 16 E data_out [15:0] $end
$var reg 1 F filled $end
$upscope $end
$upscope $end
$scope begin foobar[4] $end
$scope module stage_I $end
$var wire 1 $ clk $end
$var wire 16 G fill_in [15:0] $end
$var wire 16 H fwd_in [15:0] $end
$var wire 1 I next_filled $end
$var wire 1 J prev_filled $end
$var wire 1 & res_n $end
$var wire 1 ' shift_in $end
$var wire 1 ( shift_out $end
$var reg 16 K data_out [15:0] $end
$var reg 1 L filled $end
$upscope $end
$upscope $end
$scope begin foobar[5] $end
$scope module stage_I $end
$var wire 1 $ clk $end
$var wire 16 M fill_in [15:0] $end
$var wire 16 N fwd_in [15:0] $end
$var wire 1 O next_filled $end
$var wire 1 P prev_filled $end
$var wire 1 & res_n $end
$var wire 1 ' shift_in $end
$var wire 1 ( shift_out $end
$var reg 16 Q data_out [15:0] $end
$var reg 1 R filled $end
$upscope $end
$upscope $end
$scope begin foobar[6] $end
$scope module stage_I $end
$var wire 1 $ clk $end
$var wire 16 S fill_in [15:0] $end
$var wire 16 T fwd_in [15:0] $end
$var wire 1 U next_filled $end
$var wire 1 V prev_filled $end
$var wire 1 & res_n $end
$var wire 1 ' shift_in $end
$var wire 1 ( shift_out $end
$var reg 16 W data_out [15:0] $end
$var reg 1 X filled $end
$upscope $end
$upscope $end
$scope begin foobar[7] $end
$scope module stage_I $end
$var wire 1 $ clk $end
$var wire 16 Y fill_in [15:0] $end
$var wire 16 Z fwd_in [15:0] $end
$var wire 1 [ next_filled $end
$var wire 1 \ prev_filled $end
$var wire 1 & res_n $end
$var wire 1 ' shift_in $end
$var wire 1 ( shift_out $end
$var reg 16 ] data_out [15:0] $end
$var reg 1 ^ filled $end
$upscope $end
$upscope $end
$scope begin foobar[8] $end
$scope module stage_I $end
$var wire 1 $ clk $end
$var wire 16 _ fill_in [15:0] $end
$var wire 16 ` fwd_in [15:0] $end
$var wire 1 a next_filled $end
$var wire 1 b prev_filled $end
$var wire 1 & res_n $end
$var wire 1 ' shift_in $end
$var wire 1 ( shift_out $end
$var reg 16 c data_out [15:0] $end
$var reg 1 d filled $end
$upscope $end
$upscope $end
$scope begin foobar[9] $end
$scope module stage_I $end
$var wire 1 $ clk $end
$var wire 16 e fill_in [15:0] $end
$var wire 16 f fwd_in [15:0] $end
$var wire 1 g next_filled $end
$var wire 1 h prev_filled $end
$var wire 1 & res_n $end
$var wire 1 ' shift_in $end
$var wire 1 ( shift_out $end
$var reg 16 i data_out [15:0] $end
$var reg 1 j filled $end
$upscope $end
$upscope $end
$upscope $end
$scope task check_fifo $end
$var reg 1 k empty $end
$var reg 1 l expected_empty $end
$var reg 1 m expected_full $end
$var reg 16 n expected_outdata [15:0] $end
$var reg 1 o full $end
$var reg 16 p outdata [15:0] $end
$var reg 1 q shift_out $end
$upscope $end
$scope task defeat $end
$upscope $end
$scope task fail $end
$upscope $end
$scope task pass $end
$upscope $end
$scope task resync $end
$upscope $end
$scope task success $end
$upscope $end
$upscope $end
$enddefinitions $end
#0
$dumpvars
xq
bx p
xo
bx n
xm
xl
xk
0j
b0 i
0h
1g
b0 f
b0 e
0d
b0 c
0b
0a
b0 `
b0 _
0^
b0 ]
0\
0[
b0 Z
b0 Y
0X
b0 W
0V
0U
b0 T
b0 S
0R
b0 Q
0P
0O
b0 N
b0 M
0L
b0 K
0J
0I
b0 H
b0 G
0F
b0 E
0D
0C
b0 B
b0 A
0@
b0 ?
0>
0=
b0 <
b0 ;
0:
b0 9
08
07
b0 6
b0 5
04
b0 3
02
01
b0 0
b0 /
bx .
b100000000000 -
b0 ,
b0 +
b11111111111111111111111111111111 *
b0 )
0(
0'
0&
b0 %
1$
1#
0"
b0 !
$end
#1
b1011 .
#5
b1010111111111110 %
b1010111111111110 ,
b1010111111111110 /
b1010111111111110 5
b1010111111111110 ;
b1010111111111110 A
b1010111111111110 G
b1010111111111110 M
b1010111111111110 S
b1010111111111110 Y
b1010111111111110 _
b1010111111111110 e
1'
1&
b0 *
1l
0m
1k
0o
b0 p
0q
0$
#10
0#
1a
b110000000000 -
1j
b1010111111111110 !
b1010111111111110 +
b1010111111111110 i
1$
#11
b1011 .
#15
b1100101011111110 %
b1100101011111110 ,
b1100101011111110 /
b1100101011111110 5
b1100101011111110 ;
b1100101011111110 A
b1100101011111110 G
b1100101011111110 M
b1100101011111110 S
b1100101011111110 Y
b1100101011111110 _
b1100101011111110 e
0$
b1 *
0l
b1010111111111110 n
0k
b1010111111111110 p
#20
1h
1[
b111000000000 -
1d
b1100101011111110 c
b1100101011111110 f
1$
#21
b1011 .
#25
b1011101010111110 %
b1011101010111110 ,
b1011101010111110 /
b1011101010111110 5
b1011101010111110 ;
b1011101010111110 A
b1011101010111110 G
b1011101010111110 M
b1011101010111110 S
b1011101010111110 Y
b1011101010111110 _
b1011101010111110 e
0$
b10 *
#30
1b
1U
b111100000000 -
1^
b1011101010111110 ]
b1011101010111110 `
1$
#31
b1011 .
#35
b1011000000001011 %
b1011000000001011 ,
b1011000000001011 /
b1011000000001011 5
b1011000000001011 ;
b1011000000001011 A
b1011000000001011 G
b1011000000001011 M
b1011000000001011 S
b1011000000001011 Y
b1011000000001011 _
b1011000000001011 e
0$
b11 *
#40
1\
1O
b111110000000 -
1X
b1011000000001011 W
b1011000000001011 Z
1$
#41
b1011 .
#45
b1100000000000001 %
b1100000000000001 ,
b1100000000000001 /
b1100000000000001 5
b1100000000000001 ;
b1100000000000001 A
b1100000000000001 G
b1100000000000001 M
b1100000000000001 S
b1100000000000001 Y
b1100000000000001 _
b1100000000000001 e
0$
b100 *
#50
1V
1I
b111111000000 -
1R
b1100000000000001 Q
b1100000000000001 T
1$
#51
b1011 .
#55
b1111000000001101 %
b1111000000001101 ,
b1111000000001101 /
b1111000000001101 5
b1111000000001101 ;
b1111000000001101 A
b1111000000001101 G
b1111000000001101 M
b1111000000001101 S
b1111000000001101 Y
b1111000000001101 _
b1111000000001101 e
0$
b101 *
#60
1P
1C
b111111100000 -
1L
b1111000000001101 K
b1111000000001101 N
1$
#61
b1011 .
#65
b1101111010101101 %
b1101111010101101 ,
b1101111010101101 /
b1101111010101101 5
b1101111010101101 ;
b1101111010101101 A
b1101111010101101 G
b1101111010101101 M
b1101111010101101 S
b1101111010101101 Y
b1101111010101101 _
b1101111010101101 e
0$
b110 *
#70
1J
1=
b111111110000 -
1F
b1101111010101101 E
b1101111010101101 H
1$
#71
b1011 .
#75
b1011111011101111 %
b1011111011101111 ,
b1011111011101111 /
b1011111011101111 5
b1011111011101111 ;
b1011111011101111 A
b1011111011101111 G
b1011111011101111 M
b1011111011101111 S
b1011111011101111 Y
b1011111011101111 _
b1011111011101111 e
0$
b111 *
#80
1D
17
b111111111000 -
1@
b1011111011101111 ?
b1011111011101111 B
1$
#81
b1011 .
#85
b1100000011011110 %
b1100000011011110 ,
b1100000011011110 /
b1100000011011110 5
b1100000011011110 ;
b1100000011011110 A
b1100000011011110 G
b1100000011011110 M
b1100000011011110 S
b1100000011011110 Y
b1100000011011110 _
b1100000011011110 e
0$
b1000 *
#90
1>
11
b111111111100 -
1:
b1100000011011110 9
b1100000011011110 <
1$
#91
b1011 .
#95
b1111101000010001 %
b1111101000010001 ,
b1111101000010001 /
b1111101000010001 5
b1111101000010001 ;
b1111101000010001 A
b1111101000010001 G
b1111101000010001 M
b1111101000010001 S
b1111101000010001 Y
b1111101000010001 _
b1111101000010001 e
0$
b1001 *
#100
1"
18
b111111111110 -
14
b1111101000010001 3
b1111101000010001 6
1$
#101
b1011 .
#105
0'
0$
1m
1o
#110
1$
#111
b1011 .
#115
0$
#120
1$
#121
b1011 .
#125
0$
#130
1$
#131
b1011 .
#135
0$
#140
1$
#141
b1011 .
#145
0$
#150
1$
#151
b1011 .
#155
1(
0$
b1 )
#160
0"
08
b111111111100 -
04
b0 3
b0 6
b1111101000010001 9
b1111101000010001 <
b1100000011011110 ?
b1100000011011110 B
b1011111011101111 E
b1011111011101111 H
b1101111010101101 K
b1101111010101101 N
b1111000000001101 Q
b1111000000001101 T
b1100000000000001 W
b1100000000000001 Z
b1011000000001011 ]
b1011000000001011 `
b1011101010111110 c
b1011101010111110 f
b1100101011111110 !
b1100101011111110 +
b1100101011111110 i
1$
#161
b1011 .
#165
0$
b10 )
0m
b1100101011111110 n
0o
b1100101011111110 p
1q
#170
0>
01
b1011101010111110 !
b1011101010111110 +
b1011101010111110 i
b1011000000001011 c
b1011000000001011 f
b1100000000000001 ]
b1100000000000001 `
b1111000000001101 W
b1111000000001101 Z
b1101111010101101 Q
b1101111010101101 T
b1011111011101111 K
b1011111011101111 N
b1100000011011110 E
b1100000011011110 H
b1111101000010001 ?
b1111101000010001 B
b111111111000 -
0:
b0 9
b0 <
1$
#171
b1011 .
#175
0$
b11 )
b1011101010111110 n
b1011101010111110 p
#180
0D
07
b111111110000 -
0@
b0 ?
b0 B
b1111101000010001 E
b1111101000010001 H
b1100000011011110 K
b1100000011011110 N
b1011111011101111 Q
b1011111011101111 T
b1101111010101101 W
b1101111010101101 Z
b1111000000001101 ]
b1111000000001101 `
b1100000000000001 c
b1100000000000001 f
b1011000000001011 !
b1011000000001011 +
b1011000000001011 i
1$
#181
b1011 .
#185
0$
b100 )
b1011000000001011 n
b1011000000001011 p
#190
0J
0=
b1100000000000001 !
b1100000000000001 +
b1100000000000001 i
b1111000000001101 c
b1111000000001101 f
b1101111010101101 ]
b1101111010101101 `
b1011111011101111 W
b1011111011101111 Z
b1100000011011110 Q
b1100000011011110 T
b1111101000010001 K
b1111101000010001 N
b111111100000 -
0F
b0 E
b0 H
1$
#191
b1011 .
#195
0$
b101 )
b1100000000000001 n
b1100000000000001 p
#200
0P
0C
b111111000000 -
0L
b0 K
b0 N
b1111101000010001 Q
b1111101000010001 T
b1100000011011110 W
b1100000011011110 Z
b1011111011101111 ]
b1011111011101111 `
b1101111010101101 c
b1101111010101101 f
b1111000000001101 !
b1111000000001101 +
b1111000000001101 i
1$
#201
b1011 .
#205
0$
b110 )
b1111000000001101 n
b1111000000001101 p
#210
0V
0I
b1101111010101101 !
b1101111010101101 +
b1101111010101101 i
b1011111011101111 c
b1011111011101111 f
b1100000011011110 ]
b1100000011011110 `
b1111101000010001 W
b1111101000010001 Z
b111110000000 -
0R
b0 Q
b0 T
1$
#211
b1011 .
#215
0$
b111 )
b1101111010101101 n
b1101111010101101 p
#220
0\
0O
b111100000000 -
0X
b0 W
b0 Z
b1111101000010001 ]
b1111101000010001 `
b1100000011011110 c
b1100000011011110 f
b1011111011101111 !
b1011111011101111 +
b1011111011101111 i
1$
#221
b1011 .
#225
0$
b1000 )
b1011111011101111 n
b1011111011101111 p
#230
0b
0U
b1100000011011110 !
b1100000011011110 +
b1100000011011110 i
b1111101000010001 c
b1111101000010001 f
b111000000000 -
0^
b0 ]
b0 `
1$
#231
b1011 .
#235
0$
b1001 )
b1100000011011110 n
b1100000011011110 p
#240
0h
0[
b110000000000 -
0d
b0 c
b0 f
b1111101000010001 !
b1111101000010001 +
b1111101000010001 i
1$
#241
b1011 .
#245
0$
b1010 )
b1111101000010001 n
b1111101000010001 p
#250
1#
0a
b100000000000 -
0j
b0 !
b0 +
b0 i
1$
#251
b1011 .
#255
0(
b1111101011001110 %
b1111101011001110 ,
b1111101011001110 /
b1111101011001110 5
b1111101011001110 ;
b1111101011001110 A
b1111101011001110 G
b1111101011001110 M
b1111101011001110 S
b1111101011001110 Y
b1111101011001110 _
b1111101011001110 e
1'
0$
b1010 *
1l
bx n
1k
b0 p
#260
0#
1a
b110000000000 -
1j
b1111101011001110 !
b1111101011001110 +
b1111101011001110 i
1$
#261
b1011 .
#265
b1111111011100001 %
b1111111011100001 ,
b1111111011100001 /
b1111111011100001 5
b1111111011100001 ;
b1111111011100001 A
b1111111011100001 G
b1111111011100001 M
b1111111011100001 S
b1111111011100001 Y
b1111111011100001 _
b1111111011100001 e
0$
b1011 *
0l
b1111101011001110 n
0k
b1111101011001110 p
0q
#270
1h
1[
b111000000000 -
1d
b1111111011100001 c
b1111111011100001 f
1$
#271
b1011 .
#275
b100100011 %
b100100011 ,
b100100011 /
b100100011 5
b100100011 ;
b100100011 A
b100100011 G
b100100011 M
b100100011 S
b100100011 Y
b100100011 _
b100100011 e
0$
b1100 *
#280
1b
1U
b111100000000 -
1^
b100100011 ]
b100100011 `
1$
#281
b1011 .
#285
b100010101100111 %
b100010101100111 ,
b100010101100111 /
b100010101100111 5
b100010101100111 ;
b100010101100111 A
b100010101100111 G
b100010101100111 M
b100010101100111 S
b100010101100111 Y
b100010101100111 _
b100010101100111 e
0$
b1101 *
#290
1\
1O
b111110000000 -
1X
b100010101100111 W
b100010101100111 Z
1$
#291
b1011 .
#295
b1000100110101011 %
b1000100110101011 ,
b1000100110101011 /
b1000100110101011 5
b1000100110101011 ;
b1000100110101011 A
b1000100110101011 G
b1000100110101011 M
b1000100110101011 S
b1000100110101011 Y
b1000100110101011 _
b1000100110101011 e
0$
b1110 *
#300
1V
1I
b111111000000 -
1R
b1000100110101011 Q
b1000100110101011 T
1$
#301
b1011 .
#305
0'
0$
#310
1$
#311
b1011 .
#315
0$
#320
1$
#321
b1011 .
#325
0$
#330
1$
#331
b1011 .
#335
0$
#340
1$
#341
b1011 .
#345
0$
#350
1$
#351
b1011 .
#355
1(
0$
b1011 )
