ex5/register_stage.v
module register_stage #(parameter WIDTH=32) (input wire clk, input wire res_n,
                                   input wire[WIDTH-1:0] fill_in, input wire[WIDTH-1:0] fwd_in, output reg[WIDTH-1:0] data_out,
                                   input wire shift_in, input wire shift_out,
                                   input wire prev_filled, output reg filled, input wire next_filled
                                  );

	always @(posedge clk or negedge res_n)
	begin
		if (res_n == 1'b0)
		begin
			data_out <= {WIDTH{1'b0}};
			filled <= 1'b0;
		end
		else
		begin
			case({shift_in,shift_out})
				2'b00: // Do nothing
				begin
					data_out <= data_out;
					filled <= filled;
				end
				2'b01: // All register stages shift one forward.
				begin
					data_out <= fwd_in;
					filled <= prev_filled;
				end
				2'b10: // Fill in a new value without shifting.
				begin
					if(prev_filled == 1'b0 && filled == 1'b0 && next_filled == 1'b1)
					begin // Fill in if this stage is the first empty one ...
						data_out <= fill_in;
						filled <= 1'b1;
					end
					else
					begin // ... and keep the old value if either filled, or empty but not the first empty one.
						data_out <= data_out;
						filled <= filled;
					end
				end
				2'b11:
				begin
					if(prev_filled == 1'b0 && filled == 1'b1 && next_filled == 1'b1)
					begin // Fill in if this stage WILL be the first empty one ...
						data_out <= fill_in;
						filled <= 1'b1;
					end
					else
					begin // ... or shift the value
						data_out <= fwd_in;
						filled <= prev_filled;
					end
				end
			endcase
		end
	end
endmodule

ex5/fifo.v
`default_nettype none
module fifo #(parameter WIDTH=32, parameter DEPTH=8) (input wire clk, input wire res_n,
                                                      input wire[WIDTH-1:0] wdata, output wire[WIDTH-1:0] rdata,
                                                      input wire shift_in, input wire shift_out,
                                                      output wire full, output wire empty
                                                     );

wire[WIDTH-1:0] data [DEPTH:0];
wire[DEPTH+1:0] filled;

assign full  = filled[1];
assign empty = !filled[DEPTH];

assign data[0] = {WIDTH{1'b1}}; // For debugging: If there are all ones, they must have come from here...
assign rdata = data[DEPTH];
assign filled[0]       = 1'b0;
assign filled[DEPTH+1] = 1'b1;

generate
	genvar i;
	for(i=0; i<DEPTH; i=i+1)
	begin : foobar
		//$display("asdf");
		register_stage #(.WIDTH(WIDTH)) stage_I (.clk(clk), .res_n(res_n),
		                           .fill_in(wdata), .fwd_in(data[i]), .data_out(data[i+1]),
		                           .shift_in(shift_in), .shift_out(shift_out),
		                           .prev_filled(filled[i]), .filled(filled[i+1]), .next_filled(filled[i+2])
		                          );
	end
endgenerate


`ifdef DEBUG
always @(posedge clk)
begin
	if(full == 1'b1 && shift_in == 1'b1 && res_n == 1'b1)
		$display("%c[1;33m%m: Dropping 0x%h, because the FIFO is full.%c[0m", 27, wdata, 27);
	if(empty == 1'b1 && shift_out == 1'b1 && res_n == 1'b1)
		$display("%c[1;33m%m: Returning invalid value due to readout of empty FIFO.%c[0m", 27, 27);
	if(res_n == 1'b0 && (shift_in == 1'b1 || shift_out == 1'b1))
		$display("%c[1;33m%m: Trying to access FIFO while it is in reset.%c[0m", 27, 27);
end
`endif

`ifdef VERBOSE

integer j;
always @(posedge clk)
begin
	$write("%c[1;34m%m: STATUS:", 27);
	if(shift_in == 1'b1)
		$write(" => %h ", wdata);
	else
		$write(" -> %h ", wdata);
	for (j = 1; j != DEPTH+1; j = j + 1)
	begin
		if(filled[j] == 1'b1)
			$write("■");
		else
			$write("◻");
	end
	if(shift_out == 1'b1)
		$write(" => %h", rdata);
	else
		$write(" -> %h", rdata);
	if(full == 1'b1)
		$write(" FULL");
	if(empty == 1'b1)
		$write(" EMPTY");
	if(res_n == 1'b0)
		$write(" RESET");
	$display("%c[0m", 27);
end
`endif

endmodule

ex5/fifo_tb.v
		//$write(" ◻◼▯■□●◯◾◾◽ Address = %g",j);
`default_nettype none
`timescale 1ns/1ns

module fifo_tb;
parameter TESTWIDTH=16;
parameter TESTDEPTH=10;
	//{{{
	/* Make a regular pulsing clock. */
	parameter clk_period=10;
	parameter half_clk_period=5;
	//parameter half_clk_period=clk_period*0.5;
	reg clk = 1;
	always begin
		#half_clk_period
		//$display("clk \\");
		clk = 1'b0;

		#half_clk_period
		`ifdef SHOWCLOCK
			$display("clk /");
		`endif
		clk = 1'b1;
	end
	//}}}




	/* Make a reset that pulses once. */
	reg res_n = 0;

	reg[TESTWIDTH-1:0] indata={TESTWIDTH{1'b0}};
	wire[TESTWIDTH-1:0] outdata;
	reg shift_in;
	reg shift_out;
	wire full;
	wire empty;

	fifo #(.WIDTH(TESTWIDTH), .DEPTH(TESTDEPTH)) fifo_I(.clk(clk), .res_n(res_n),
	                                            .wdata(indata), .rdata(outdata),
	                                            .shift_in(shift_in), .shift_out(shift_out),
	                                            .full(full), .empty(empty)
	                                           );

//	task print_status(input[TESTWIDTH-1:0] outdata, input full, input empty);
//	begin
//		if(full == 1'b0 && empty == 1'b0)
//			$display("%t: output=%h",$time, outdata);
//		if(full == 1'b0 && empty == 1'b1)
//			$display("%t: output=%h EMPTY",$time, outdata);
//		if(full == 1'b1 && empty == 1'b0)
//			$display("%t: output=%h FULL",$time, outdata);
//		if(full == 1'b1 && empty == 1'b1)
//			$display("%t: output=%h FULL EMPTY",$time, outdata);
//	end
//	endtask
//	always @(outdata, full, empty) begin
//		print_status(outdata, full, empty);
//	end



//{{{ Messages, pretty printed

	task pass;
	begin
		$display("%c[1;34m",27);
		$display("***************************************");
		$display("*********** TEST CASE PASS ************");
		$display("***************************************");
		$write("%c[0m",27);
	end
	endtask

	task fail;
	begin
		$display("%c[1;31m",27);
		$display("***************************************");
		$display("*********** TEST CASE FAIL ************");
		$display("***************************************");
		$display("%c[0m",27);
		`ifdef FAILABORT
			$finish;
		`endif
	end
	endtask

	task success;
	begin
			$display("%c[1;32m-----------------------------------------------------------> SUCCESS.%c[0m", 27, 27);
	end
	endtask

	task defeat;
	begin
			$display("%c[1;31m-----------------------------------------------------------> FAILED.%c[0m", 27, 27);
			fail;
	end
	endtask
//}}}



	task check_fifo(input shift_out, input[TESTWIDTH-1:0] outdata, input full, input empty, input[TESTWIDTH-1:0] expected_outdata, input expected_full, input expected_empty);
	begin
		if(full === 1'b1 && empty === 1'b1)
		begin
			$display("%c[1;31mFIFO TEST: EMPTY and FULL at the same time.%c[0m", 27, 27);
			defeat;
		end
		if(full !== expected_full)
		begin
			$display("%c[1;31mFIFO TEST: Expected full = %b but got %b.%c[0m", 27, expected_full, full, 27);
			defeat;
		end
		if(empty !== expected_empty)
		begin
			$display("%c[1;31mFIFO TEST: Expected empty = %b but got %b.%c[0m", 27, expected_empty, empty, 27);
			defeat;
		end
		if(^expected_outdata!==1'bX && expected_empty == 1'b0 && shift_out == 1'b1 && outdata !== expected_outdata)
		begin
			$display("%c[1;31mFIFO TEST: Expected output = %h but got %h.%c[0m", 27, expected_outdata, outdata, 27);
			defeat;
		end
	end
	endtask







// Jeweils alle Kombinationen von shift_in, shift_out und reset für die Füllstände "Leer" "Ein Element" "Halbvoll" "Fast voll" und "Voll".
// Für echte Hardware zusätzlich noch Test, ob der Fifo bei bestimmten Daten Probleme bekommt (Siehe FDIV-Bug).


reg[TESTWIDTH-1:0] TESTVECTOR[TESTDEPTH*2+5:0];

integer write=-1;
integer read=0;
integer i=0;
	initial begin
	$dumpfile("fifo.vcd");
	$dumpvars(0, fifo_tb);
	TESTVECTOR[ 0] = 16'haffe;
	TESTVECTOR[ 1] = 16'hcafe;
	TESTVECTOR[ 2] = 16'hbabe;
	TESTVECTOR[ 3] = 16'hb00b;
	TESTVECTOR[ 4] = 16'hc001;
	TESTVECTOR[ 5] = 16'hf00d;
	TESTVECTOR[ 6] = 16'hdead;
	TESTVECTOR[ 7] = 16'hbeef;
	TESTVECTOR[ 8] = 16'hc0de;
	TESTVECTOR[ 9] = 16'hfa11;
	TESTVECTOR[10] = 16'hface;
	TESTVECTOR[11] = 16'hfee1;
	TESTVECTOR[12] = 16'h0123;
	TESTVECTOR[13] = 16'h4567;
	TESTVECTOR[14] = 16'h89ab;
	TESTVECTOR[15] = 16'hcdef;
	TESTVECTOR[16] = 16'h1111;
	TESTVECTOR[17] = 16'h2222;
	TESTVECTOR[18] = 16'h3333;
	TESTVECTOR[19] = 16'h4444;
	TESTVECTOR[20] = 16'h5555;
	TESTVECTOR[21] = 16'h6666;
	TESTVECTOR[22] = 16'h7777;
	TESTVECTOR[23] = 16'h8888;
	TESTVECTOR[24] = 16'h9999;
	TESTVECTOR[25] = 16'ha5a5;

	shift_in  <= 1'b0;
	shift_out <= 1'b0;
	indata <= {TESTWIDTH{1'b0}};
	#half_clk_period
	res_n <= 1;

	$display("STARTING Shift_in TEST:");
	check_fifo(shift_out, outdata, full, empty, 16'hxxxx, 0, 1);

	repeat(TESTDEPTH-1)
	begin
		shift_in = 1; write++;
		indata <= TESTVECTOR[write][TESTWIDTH-1:0];
		shift_out <= 0;// read++;
		#clk_period;
		check_fifo(shift_out, outdata, full, empty, TESTVECTOR[read][TESTWIDTH-1:0], 0, 0);
	end
	shift_in = 1; write++;
	indata <= TESTVECTOR[write][TESTWIDTH-1:0];
	shift_out <= 0;// read++;
	#clk_period;
	check_fifo(shift_out, outdata, full, empty, TESTVECTOR[read][TESTWIDTH-1:0], 1, 0);

	// NOP to see the full state shown
	shift_in = 0; //write++;
	indata <= TESTVECTOR[write][TESTWIDTH-1:0];
	shift_out <= 0;// read++;
	#clk_period;
	check_fifo(shift_out, outdata, full, empty, TESTVECTOR[read][TESTWIDTH-1:0], 1, 0);
	success;

	$display("STARTING FULL NOP TEST:");
	repeat(5)
	begin
		shift_in = 0; //write++;
		indata <= TESTVECTOR[write][TESTWIDTH-1:0];
		shift_out <= 0;// read++;
		#clk_period;
		check_fifo(shift_out, outdata, full, empty, TESTVECTOR[read][TESTWIDTH-1:0], 1, 0);
	end
	success;

	$display("STARTING Shift_out TEST:");
	repeat(TESTDEPTH-1)
	begin
		shift_in = 0; //write++;
		indata <= TESTVECTOR[write][TESTWIDTH-1:0];
		shift_out <= 1; read++;
		#clk_period;
		check_fifo(shift_out, outdata, full, empty, TESTVECTOR[read][TESTWIDTH-1:0], 0, 0);
	end
	shift_in = 0; //write++;
	indata <= TESTVECTOR[write][TESTWIDTH-1:0];
	shift_out <= 1; read++;
	#clk_period;
	check_fifo(shift_out, outdata, full, empty, TESTVECTOR[read][TESTWIDTH-1:0], 0, 1);

	// NOP to see the empty state shown
	shift_in = 0; //write++;
	indata <= TESTVECTOR[write][TESTWIDTH-1:0];
	shift_out <= 0; //read++;
	#clk_period;
	check_fifo(shift_out, outdata, full, empty, TESTVECTOR[read][TESTWIDTH-1:0], 0, 1);
	success;

	$display("STARTING EMPTY NOP TEST:");
	repeat(5)
	begin
		shift_in = 0; //write++;
		indata <= TESTVECTOR[write][TESTWIDTH-1:0];
		shift_out <= 0;// read++;
		#clk_period;
		check_fifo(shift_out, outdata, full, empty, 16'hxxxx, 0, 1);
	end
	success;

	$display("STARTING UNDERFILL TEST:");
	// FIFO is empty now
	`ifdef DEBUG
		$display("%c[1;33mThere should be 5 debug message here, each saying that invalid data from an empty FIFO is returned.%c[0m", 27, 27);
	`endif
	repeat(5)
	begin
		shift_in = 0; //write++;
		indata <= TESTVECTOR[write][TESTWIDTH-1:0];
		shift_out <= 1;// read++;
		#clk_period;
		check_fifo(shift_out, outdata, full, empty, TESTVECTOR[read][TESTWIDTH-1:0], 0, 1);
	end
	success;

	$display("STARTING OVERFILL TEST:");
	write=-1;
	read=0;
	check_fifo(shift_out, outdata, full, empty, 16'hxxxx, 0, 1);
	shift_in = 1; write++;
	indata <= TESTVECTOR[write][TESTWIDTH-1:0];
	shift_out <= 0;// read++;
	#clk_period;

	repeat(TESTDEPTH-1)
	begin
		check_fifo(shift_out, outdata, full, empty, TESTVECTOR[read][TESTWIDTH-1:0], 0, 0);
		shift_in = 1; write++;
		indata <= TESTVECTOR[write][TESTWIDTH-1:0];
		shift_out <= 0;// read++;
		#clk_period;
	end


	check_fifo(shift_out, outdata, full, empty, TESTVECTOR[read][TESTWIDTH-1:0], 1, 0);
	shift_in = 0; //write++;
	indata <= TESTVECTOR[write][TESTWIDTH-1:0];
	shift_out <= 0;// read++;
	#clk_period;

	// FIFO is full now

	`ifdef DEBUG
		$display("%c[1;33mThere should be 5 debug message here, each saying that a data member was dropped.%c[0m", 27, 27);
	`endif
	repeat(5)
	begin
		check_fifo(shift_out, outdata, full, empty, TESTVECTOR[read][TESTWIDTH-1:0], 1, 0);
		shift_in = 1; //write++;
		indata <= TESTVECTOR[write][TESTWIDTH-1:0];
		shift_out <= 0;// read++;
		#clk_period;
	end
	check_fifo(shift_out, outdata, full, empty, TESTVECTOR[read][TESTWIDTH-1:0], 1, 0);
	shift_in = 0; //write++;
	indata <= TESTVECTOR[write][TESTWIDTH-1:0];
	shift_out <= 1; read++;
	#clk_period;

	repeat(TESTDEPTH-1)
	begin
		check_fifo(shift_out, outdata, full, empty, TESTVECTOR[read][TESTWIDTH-1:0], 0, 0);
		shift_in = 0; //write++;
		indata <= TESTVECTOR[write][TESTWIDTH-1:0];
		shift_out <= 1; read++;
		#clk_period;
	end

	check_fifo(shift_out, outdata, full, empty, TESTVECTOR[read][TESTWIDTH-1:0], 0, 1);
	shift_in = 0; //write++;
	indata <= TESTVECTOR[write][TESTWIDTH-1:0];
	shift_out <= 0; //read++;
	#clk_period;
	success;


	$display("STARTING EMPTY RESET TEST:");
	write=-1; // Restart the test pattern
	read=0;

	#2 res_n = 0; // Generate a short spike on the reset line
	#1 res_n = 1;


	check_fifo(shift_out, outdata, full, empty, {TESTWIDTH{1'b0}}, 0, 1);
	shift_in = 0; //write++;
	indata <= TESTVECTOR[write][TESTWIDTH-1:0];
	shift_out <= 0; //read++;
	#clk_period;
	check_fifo(shift_out, outdata, full, empty, {TESTWIDTH{1'b0}}, 0, 1);









	success;






	//#10
	$finish;
	end







	//initial $monitor("%t: output: %h (%0d)", $time, outdata, value);



endmodule

ex5/fifo.vcd
$date
	Mon Feb  1 15:21:43 2016
$end
$version
	Icarus Verilog
$end
$timescale
	1ns
$end
$scope module fifo_tb $end
$var wire 16 ! outdata [15:0] $end
$var wire 1 " full $end
$var wire 1 # empty $end
$var reg 1 $ clk $end
$var reg 16 % indata [15:0] $end
$var reg 1 & res_n $end
$var reg 1 ' shift_in $end
$var reg 1 ( shift_out $end
$var integer 32 ) i [31:0] $end
$var integer 32 * read [31:0] $end
$var integer 32 + write [31:0] $end
$scope module fifo_I $end
$var wire 1 $ clk $end
$var wire 16 , rdata [15:0] $end
$var wire 1 & res_n $end
$var wire 1 ' shift_in $end
$var wire 1 ( shift_out $end
$var wire 16 - wdata [15:0] $end
$var wire 1 " full $end
$var wire 12 . filled [11:0] $end
$var wire 1 # empty $end
$var integer 32 / j [31:0] $end
$scope begin foobar[0] $end
$scope module stage_I $end
$var wire 1 $ clk $end
$var wire 16 0 fill_in [15:0] $end
$var wire 16 1 fwd_in [15:0] $end
$var wire 1 2 next_filled $end
$var wire 1 3 prev_filled $end
$var wire 1 & res_n $end
$var wire 1 ' shift_in $end
$var wire 1 ( shift_out $end
$var reg 16 4 data_out [15:0] $end
$var reg 1 5 filled $end
$upscope $end
$upscope $end
$scope begin foobar[1] $end
$scope module stage_I $end
$var wire 1 $ clk $end
$var wire 16 6 fill_in [15:0] $end
$var wire 16 7 fwd_in [15:0] $end
$var wire 1 8 next_filled $end
$var wire 1 9 prev_filled $end
$var wire 1 & res_n $end
$var wire 1 ' shift_in $end
$var wire 1 ( shift_out $end
$var reg 16 : data_out [15:0] $end
$var reg 1 ; filled $end
$upscope $end
$upscope $end
$scope begin foobar[2] $end
$scope module stage_I $end
$var wire 1 $ clk $end
$var wire 16 < fill_in [15:0] $end
$var wire 16 = fwd_in [15:0] $end
$var wire 1 > next_filled $end
$var wire 1 ? prev_filled $end
$var wire 1 & res_n $end
$var wire 1 ' shift_in $end
$var wire 1 ( shift_out $end
$var reg 16 @ data_out [15:0] $end
$var reg 1 A filled $end
$upscope $end
$upscope $end
$scope begin foobar[3] $end
$scope module stage_I $end
$var wire 1 $ clk $end
$var wire 16 B fill_in [15:0] $end
$var wire 16 C fwd_in [15:0] $end
$var wire 1 D next_filled $end
$var wire 1 E prev_filled $end
$var wire 1 & res_n $end
$var wire 1 ' shift_in $end
$var wire 1 ( shift_out $end
$var reg 16 F data_out [15:0] $end
$var reg 1 G filled $end
$upscope $end
$upscope $end
$scope begin foobar[4] $end
$scope module stage_I $end
$var wire 1 $ clk $end
$var wire 16 H fill_in [15:0] $end
$var wire 16 I fwd_in [15:0] $end
$var wire 1 J next_filled $end
$var wire 1 K prev_filled $end
$var wire 1 & res_n $end
$var wire 1 ' shift_in $end
$var wire 1 ( shift_out $end
$var reg 16 L data_out [15:0] $end
$var reg 1 M filled $end
$upscope $end
$upscope $end
$scope begin foobar[5] $end
$scope module stage_I $end
$var wire 1 $ clk $end
$var wire 16 N fill_in [15:0] $end
$var wire 16 O fwd_in [15:0] $end
$var wire 1 P next_filled $end
$var wire 1 Q prev_filled $end
$var wire 1 & res_n $end
$var wire 1 ' shift_in $end
$var wire 1 ( shift_out $end
$var reg 16 R data_out [15:0] $end
$var reg 1 S filled $end
$upscope $end
$upscope $end
$scope begin foobar[6] $end
$scope module stage_I $end
$var wire 1 $ clk $end
$var wire 16 T fill_in [15:0] $end
$var wire 16 U fwd_in [15:0] $end
$var wire 1 V next_filled $end
$var wire 1 W prev_filled $end
$var wire 1 & res_n $end
$var wire 1 ' shift_in $end
$var wire 1 ( shift_out $end
$var reg 16 X data_out [15:0] $end
$var reg 1 Y filled $end
$upscope $end
$upscope $end
$scope begin foobar[7] $end
$scope module stage_I $end
$var wire 1 $ clk $end
$var wire 16 Z fill_in [15:0] $end
$var wire 16 [ fwd_in [15:0] $end
$var wire 1 \ next_filled $end
$var wire 1 ] prev_filled $end
$var wire 1 & res_n $end
$var wire 1 ' shift_in $end
$var wire 1 ( shift_out $end
$var reg 16 ^ data_out [15:0] $end
$var reg 1 _ filled $end
$upscope $end
$upscope $end
$scope begin foobar[8] $end
$scope module stage_I $end
$var wire 1 $ clk $end
$var wire 16 ` fill_in [15:0] $end
$var wire 16 a fwd_in [15:0] $end
$var wire 1 b next_filled $end
$var wire 1 c prev_filled $end
$var wire 1 & res_n $end
$var wire 1 ' shift_in $end
$var wire 1 ( shift_out $end
$var reg 16 d data_out [15:0] $end
$var reg 1 e filled $end
$upscope $end
$upscope $end
$scope begin foobar[9] $end
$scope module stage_I $end
$var wire 1 $ clk $end
$var wire 16 f fill_in [15:0] $end
$var wire 16 g fwd_in [15:0] $end
$var wire 1 h next_filled $end
$var wire 1 i prev_filled $end
$var wire 1 & res_n $end
$var wire 1 ' shift_in $end
$var wire 1 ( shift_out $end
$var reg 16 j data_out [15:0] $end
$var reg 1 k filled $end
$upscope $end
$upscope $end
$upscope $end
$scope task check_fifo $end
$var reg 1 l empty $end
$var reg 1 m expected_empty $end
$var reg 1 n expected_full $end
$var reg 16 o expected_outdata [15:0] $end
$var reg 1 p full $end
$var reg 16 q outdata [15:0] $end
$var reg 1 r shift_out $end
$upscope $end
$scope task defeat $end
$upscope $end
$scope task fail $end
$upscope $end
$scope task pass $end
$upscope $end
$scope task success $end
$upscope $end
$upscope $end
$enddefinitions $end
#0
$dumpvars
xr
bx q
xp
bx o
xn
xm
xl
0k
b0 j
0i
1h
b0 g
b0 f
0e
b0 d
0c
0b
b0 a
b0 `
0_
b0 ^
0]
0\
b0 [
b0 Z
0Y
b0 X
0W
0V
b0 U
b0 T
0S
b0 R
0Q
0P
b0 O
b0 N
0M
b0 L
0K
0J
b0 I
b0 H
0G
b0 F
0E
0D
b0 C
b0 B
0A
b0 @
0?
0>
b0 =
b0 <
0;
b0 :
09
08
b0 7
b0 6
05
b0 4
03
02
b1111111111111111 1
b0 0
b1011 /
b100000000000 .
b0 -
b0 ,
b11111111111111111111111111111111 +
b0 *
b0 )
0(
0'
0&
b0 %
1$
1#
0"
b0 !
$end
#5
b1010111111111110 %
b1010111111111110 -
b1010111111111110 0
b1010111111111110 6
b1010111111111110 <
b1010111111111110 B
b1010111111111110 H
b1010111111111110 N
b1010111111111110 T
b1010111111111110 Z
b1010111111111110 `
b1010111111111110 f
1&
b0 +
1'
1m
0n
1l
0p
b0 q
0r
0$
#10
0#
1b
b110000000000 .
1k
b1010111111111110 !
b1010111111111110 ,
b1010111111111110 j
b1011 /
1$
#15
b1100101011111110 %
b1100101011111110 -
b1100101011111110 0
b1100101011111110 6
b1100101011111110 <
b1100101011111110 B
b1100101011111110 H
b1100101011111110 N
b1100101011111110 T
b1100101011111110 Z
b1100101011111110 `
b1100101011111110 f
0$
b1 +
0m
b1010111111111110 o
0l
b1010111111111110 q
#20
1i
1\
b111000000000 .
1e
b1100101011111110 d
b1100101011111110 g
b1011 /
1$
#25
b1011101010111110 %
b1011101010111110 -
b1011101010111110 0
b1011101010111110 6
b1011101010111110 <
b1011101010111110 B
b1011101010111110 H
b1011101010111110 N
b1011101010111110 T
b1011101010111110 Z
b1011101010111110 `
b1011101010111110 f
0$
b10 +
#30
1c
1V
b111100000000 .
1_
b1011101010111110 ^
b1011101010111110 a
b1011 /
1$
#35
b1011000000001011 %
b1011000000001011 -
b1011000000001011 0
b1011000000001011 6
b1011000000001011 <
b1011000000001011 B
b1011000000001011 H
b1011000000001011 N
b1011000000001011 T
b1011000000001011 Z
b1011000000001011 `
b1011000000001011 f
0$
b11 +
#40
1]
1P
b111110000000 .
1Y
b1011000000001011 X
b1011000000001011 [
b1011 /
1$
#45
b1100000000000001 %
b1100000000000001 -
b1100000000000001 0
b1100000000000001 6
b1100000000000001 <
b1100000000000001 B
b1100000000000001 H
b1100000000000001 N
b1100000000000001 T
b1100000000000001 Z
b1100000000000001 `
b1100000000000001 f
0$
b100 +
#50
1W
1J
b111111000000 .
1S
b1100000000000001 R
b1100000000000001 U
b1011 /
1$
#55
b1111000000001101 %
b1111000000001101 -
b1111000000001101 0
b1111000000001101 6
b1111000000001101 <
b1111000000001101 B
b1111000000001101 H
b1111000000001101 N
b1111000000001101 T
b1111000000001101 Z
b1111000000001101 `
b1111000000001101 f
0$
b101 +
#60
1Q
1D
b111111100000 .
1M
b1111000000001101 L
b1111000000001101 O
b1011 /
1$
#65
b1101111010101101 %
b1101111010101101 -
b1101111010101101 0
b1101111010101101 6
b1101111010101101 <
b1101111010101101 B
b1101111010101101 H
b1101111010101101 N
b1101111010101101 T
b1101111010101101 Z
b1101111010101101 `
b1101111010101101 f
0$
b110 +
#70
1K
1>
b111111110000 .
1G
b1101111010101101 F
b1101111010101101 I
b1011 /
1$
#75
b1011111011101111 %
b1011111011101111 -
b1011111011101111 0
b1011111011101111 6
b1011111011101111 <
b1011111011101111 B
b1011111011101111 H
b1011111011101111 N
b1011111011101111 T
b1011111011101111 Z
b1011111011101111 `
b1011111011101111 f
0$
b111 +
#80
1E
18
b111111111000 .
1A
b1011111011101111 @
b1011111011101111 C
b1011 /
1$
#85
b1100000011011110 %
b1100000011011110 -
b1100000011011110 0
b1100000011011110 6
b1100000011011110 <
b1100000011011110 B
b1100000011011110 H
b1100000011011110 N
b1100000011011110 T
b1100000011011110 Z
b1100000011011110 `
b1100000011011110 f
0$
b1000 +
#90
1?
12
b111111111100 .
1;
b1100000011011110 :
b1100000011011110 =
b1011 /
1$
#95
b1111101000010001 %
b1111101000010001 -
b1111101000010001 0
b1111101000010001 6
b1111101000010001 <
b1111101000010001 B
b1111101000010001 H
b1111101000010001 N
b1111101000010001 T
b1111101000010001 Z
b1111101000010001 `
b1111101000010001 f
0$
b1001 +
#100
1"
19
b111111111110 .
15
b1111101000010001 4
b1111101000010001 7
b1011 /
1$
#105
0$
0'
1n
1p
#110
b1011 /
1$
#115
0$
#120
b1011 /
1$
#125
0$
#130
b1011 /
1$
#135
0$
#140
b1011 /
1$
#145
0$
#150
b1011 /
1$
#155
0$
#160
b1011 /
1$
#165
1(
0$
b1 *
#170
0"
09
b1100101011111110 !
b1100101011111110 ,
b1100101011111110 j
b1011101010111110 d
b1011101010111110 g
b1011000000001011 ^
b1011000000001011 a
b1100000000000001 X
b1100000000000001 [
b1111000000001101 R
b1111000000001101 U
b1101111010101101 L
b1101111010101101 O
b1011111011101111 F
b1011111011101111 I
b1100000011011110 @
b1100000011011110 C
b1111101000010001 :
b1111101000010001 =
b111111111100 .
05
b1111111111111111 4
b1111111111111111 7
b1011 /
1$
#175
0$
b10 *
0n
b1100101011111110 o
0p
b1100101011111110 q
1r
#180
0?
02
b111111111000 .
0;
b1111111111111111 :
b1111111111111111 =
b1111101000010001 @
b1111101000010001 C
b1100000011011110 F
b1100000011011110 I
b1011111011101111 L
b1011111011101111 O
b1101111010101101 R
b1101111010101101 U
b1111000000001101 X
b1111000000001101 [
b1100000000000001 ^
b1100000000000001 a
b1011000000001011 d
b1011000000001011 g
b1011101010111110 !
b1011101010111110 ,
b1011101010111110 j
b1011 /
1$
#185
0$
b11 *
b1011101010111110 o
b1011101010111110 q
#190
0E
08
b1011000000001011 !
b1011000000001011 ,
b1011000000001011 j
b1100000000000001 d
b1100000000000001 g
b1111000000001101 ^
b1111000000001101 a
b1101111010101101 X
b1101111010101101 [
b1011111011101111 R
b1011111011101111 U
b1100000011011110 L
b1100000011011110 O
b1111101000010001 F
b1111101000010001 I
b111111110000 .
0A
b1111111111111111 @
b1111111111111111 C
b1011 /
1$
#195
0$
b100 *
b1011000000001011 o
b1011000000001011 q
#200
0K
0>
b111111100000 .
0G
b1111111111111111 F
b1111111111111111 I
b1111101000010001 L
b1111101000010001 O
b1100000011011110 R
b1100000011011110 U
b1011111011101111 X
b1011111011101111 [
b1101111010101101 ^
b1101111010101101 a
b1111000000001101 d
b1111000000001101 g
b1100000000000001 !
b1100000000000001 ,
b1100000000000001 j
b1011 /
1$
#205
0$
b101 *
b1100000000000001 o
b1100000000000001 q
#210
0Q
0D
b1111000000001101 !
b1111000000001101 ,
b1111000000001101 j
b1101111010101101 d
b1101111010101101 g
b1011111011101111 ^
b1011111011101111 a
b1100000011011110 X
b1100000011011110 [
b1111101000010001 R
b1111101000010001 U
b111111000000 .
0M
b1111111111111111 L
b1111111111111111 O
b1011 /
1$
#215
0$
b110 *
b1111000000001101 o
b1111000000001101 q
#220
0W
0J
b111110000000 .
0S
b1111111111111111 R
b1111111111111111 U
b1111101000010001 X
b1111101000010001 [
b1100000011011110 ^
b1100000011011110 a
b1011111011101111 d
b1011111011101111 g
b1101111010101101 !
b1101111010101101 ,
b1101111010101101 j
b1011 /
1$
#225
0$
b111 *
b1101111010101101 o
b1101111010101101 q
#230
0]
0P
b1011111011101111 !
b1011111011101111 ,
b1011111011101111 j
b1100000011011110 d
b1100000011011110 g
b1111101000010001 ^
b1111101000010001 a
b111100000000 .
0Y
b1111111111111111 X
b1111111111111111 [
b1011 /
1$
#235
0$
b1000 *
b1011111011101111 o
b1011111011101111 q
#240
0c
0V
b111000000000 .
0_
b1111111111111111 ^
b1111111111111111 a
b1111101000010001 d
b1111101000010001 g
b1100000011011110 !
b1100000011011110 ,
b1100000011011110 j
b1011 /
1$
#245
0$
b1001 *
b1100000011011110 o
b1100000011011110 q
#250
0i
0\
b1111101000010001 !
b1111101000010001 ,
b1111101000010001 j
b110000000000 .
0e
b1111111111111111 d
b1111111111111111 g
b1011 /
1$
#255
0$
b1010 *
b1111101000010001 o
b1111101000010001 q
#260
1#
0b
b100000000000 .
0k
b1111111111111111 !
b1111111111111111 ,
b1111111111111111 j
b1011 /
1$
#265
0(
0$
1m
b1111101011001110 o
1l
b1111111111111111 q
#270
b1011 /
1$
#275
0$
0r
#280
b1011 /
1$
#285
0$
bx o
#290
b1011 /
1$
#295
0$
#300
b1011 /
1$
#305
0$
#310
b1011 /
1$
#315
0$
#320
b1011 /
1$
#325
1(
0$
#330
b1011 /
1$
#335
0$
b1111101011001110 o
1r
#340
b1011 /
1$
#345
0$
#350
b1011 /
1$
#355
0$
#360
b1011 /
1$
#365
0$
#370
b1011 /
1$
#375
0(
b1010111111111110 %
b1010111111111110 -
b1010111111111110 0
b1010111111111110 6
b1010111111111110 <
b1010111111111110 B
b1010111111111110 H
b1010111111111110 N
b1010111111111110 T
b1010111111111110 Z
b1010111111111110 `
b1010111111111110 f
0$
1'
bx o
b0 *
b0 +
#380
0#
1b
b110000000000 .
1k
b1010111111111110 !
b1010111111111110 ,
b1010111111111110 j
b1011 /
1$
#385
b1100101011111110 %
b1100101011111110 -
b1100101011111110 0
b1100101011111110 6
b1100101011111110 <
b1100101011111110 B
b1100101011111110 H
b1100101011111110 N
b1100101011111110 T
b1100101011111110 Z
b1100101011111110 `
b1100101011111110 f
0$
b1 +
0m
b1010111111111110 o
0l
b1010111111111110 q
0r
#390
1i
1\
b111000000000 .
1e
b1100101011111110 d
b1100101011111110 g
b1011 /
1$
#395
b1011101010111110 %
b1011101010111110 -
b1011101010111110 0
b1011101010111110 6
b1011101010111110 <
b1011101010111110 B
b1011101010111110 H
b1011101010111110 N
b1011101010111110 T
b1011101010111110 Z
b1011101010111110 `
b1011101010111110 f
0$
b10 +
#400
1c
1V
b111100000000 .
1_
b1011101010111110 ^
b1011101010111110 a
b1011 /
1$
#405
b1011000000001011 %
b1011000000001011 -
b1011000000001011 0
b1011000000001011 6
b1011000000001011 <
b1011000000001011 B
b1011000000001011 H
b1011000000001011 N
b1011000000001011 T
b1011000000001011 Z
b1011000000001011 `
b1011000000001011 f
0$
b11 +
#410
1]
1P
b111110000000 .
1Y
b1011000000001011 X
b1011000000001011 [
b1011 /
1$
#415
b1100000000000001 %
b1100000000000001 -
b1100000000000001 0
b1100000000000001 6
b1100000000000001 <
b1100000000000001 B
b1100000000000001 H
b1100000000000001 N
b1100000000000001 T
b1100000000000001 Z
b1100000000000001 `
b1100000000000001 f
0$
b100 +
